Workbook
Name _CCY1: #REF!
Name _CCY2: #REF!
Name _CURMONTH: #REF!
Name _INDEX1: #REF!
Name _INDEX2: #REF!
Name _INDEX3: #REF!
Name _INDEX4: #REF!
Name _INDEX5: #REF!
Name _INDEX6: #REF!
Name _STARTMONTH: #REF!
Name _YE1: #REF!
Name _YE2: #REF!
Name _YE3: #REF!
Name _YE4: #REF!
Name _YE5: #REF!
Name _YE6: #REF!
Name _YE7: #REF!
Name _YE8: #REF!
Name _YE9: #REF!
Name afskr_soft: #REF!
Name asdf: #REF!
Name bogf_soft: #REF!
Name BtfeIndexSheetTable: #REF!
Name C_ScenNum: #REF!
Name Category_1: #REF!
Name Category_2: #REF!
Name CCY: #REF!
Name Check: #REF!
Name CheckLimit: #REF!
Name circ: #REF!
Name COGS_Keyword: #REF!
Name Convert_t: #REF!
Name Country_list: #REF!
Name Criteria_2: #REF!
Name Currency_unit: #REF!
Name Customer_info_list: #REF!
Name Denom: #REF!
Name dFilter: ""
Name engelsk: #REF!
Name EntityColumn: #REF!
Name EntityKeyword: #REF!
Name Err_Tol: #REF!
Name Filter_groups: OFFSET(#REF!,0,0,COUNTA(#REF!)-COUNTIF(#REF!,"END"))
Name Filter_headings: OFFSET(#REF!,0,0,COUNTA(#REF!)-COUNTIF(#REF!,"END"))
Name Filter_periods: #REF!
Name FTE_1: #REF!
Name FTE_10: #REF!
Name FTE_11: #REF!
Name FTE_12: #REF!
Name FTE_13: #REF!
Name FTE_14: #REF!
Name FTE_15: #REF!
Name FTE_16: #REF!
Name FTE_17: #REF!
Name FTE_18: #REF!
Name FTE_19: #REF!
Name FTE_2: #REF!
Name FTE_20: #REF!
Name FTE_21: #REF!
Name FTE_22: #REF!

Sheet Frontpage
F9: Rheinmetall
F10: Calculation workbook
F24: Bocconi
F25: Milano, italy
F26: Updated 01/10/2026

Sheet Table of contents
B3: =MID(CELL("filename",B3),FIND("]",CELL("filename",B3))+1,256) -> Table of contents
A6: x | B6: Start here
B8: Frontpage | J8: Cover
B9: Decisions to revisit (temporary tab) | J9: Choices made in Block 2 that we may reconsider; remove before hand-in
B10: Log — issue log (I-01 to I-52 Block 1; I-53 onwards Block 2) | J10: One record per conflict or analytical issue
A12: x | B12: Block 1 — reformulation (Module A, Sessions 2–6) — tab 'Reformation & Profitability'
B14: Reformulated income statement | C14: R1–R11 | J14: Core [A], non-core [B], financial [C], unusual items; value: core operating income [A]
B15: EBITDA | C15: R3–R4 | J15: Before pension interest, D&A and unusual items
B16: Unusual items | C16: R9 | J16: Every unusual item with its criterion; value: total unusual items
B17: Operating cost structure — three lenses | C17: C1–C5 | J17: By function (n.d.), external vs internal, variable vs fixed
B18: Managerial balance sheet | C18: B1–B9 | J18: NOWC, NOIC, non-operating assets, NFP, NFO; value: net operating invested capital
B19: Net operating working capital (NOWC) | C19: B4
B20: Net financial position (NFP) | C20: B6 | J20: Negative = net liquidity
B21: ROI and ROE decompositions | C21: P0–P8, E1–E7 | J21: Value: ROE = comprehensive income / net equity
B22: Ratio summary and material-change screen | C22: S0–S2 | J22: Three-year comparison with slide thresholds
B23: Checks — Block 1 | J23: Status of the Block 1 controls
A25: x | B25: Block 2 — cash flow (Module B, Sessions 7–9) — tab 'Reformation & Profitability'
B27: Reformulated cash flow statement — change in cash | C27: K10–K16 | J27: OCF, CAPEX, OFCF and other cash flows; value: OFCF before taxes
B28: Operating cash flow (OCF), before taxes | C28: K12 | J28: EBITDA ± ΔNOWC; derived from the reported CFOA
B29: From CFOA to OCF (CFOA ≠ OCF) | C29: K17 | J29: Interest, taxes, dividends and unusual items moved out of CFOA
B30: ΔNOWC: cash basis vs managerial balance sheet | C30: K11 | J30: Value: non-cash changes in NOWC
B31: Unusual items and sustainable OCF | C31: K18–K21 | J31: Value: sustainable OCF, continuing operations (indicative)
B32: Reformulated cash flow statement — change in NFP | C32: K22–K24 | J32: Three-case NFP bridge; value: cash generated
B33: Free cash flow to equity (FCFE) | C33: K25–K27 | J33: Unlevered FCF and the two finance views; value: FCFE
B34: CAPEX hidden in business combinations | C34: K28 | J34: Value: adjusted OFCF
B35: Placeholders: Sessions 10–12 (ratios, creative reporting, KPIs and peers) | J35: To be built when the slides are uploaded
B36: Checks — Block 2 | J36: Status of the Module B controls
A38: x | B38: Inputs — figures exactly as reported, with sources
B40: Reported Financials — income statement | J40: Block 1
B41: Reported Financials — balance sheet | J41: Block 1
B42: Reported Financials — notes to the balance sheet | J42: Other assets, financial debts, other liabilities, accumulated depreciation
B43: Reported Financials — how the cash flow statement is presented (K1–K4) | C43: K1–K4 | J43: IAS 7 version, method, perimeter, where interest, dividends and taxes sit
B44: Reported Financials — cash flow statement (IAS 7, complete) | J44: Value: cash flow from operating activities
B45: Reported Financials — discontinued operations (note 8)
B46: Reported Financials — business combinations (note 7)
B47: Reported Financials — §44A reconciliation of financing liabilities (note 29)
B48: Reported Financials — provisions for structural measures (note 28)
B49: Input financials — source of every number | J49: Same rows as Reported Financials; report and printed page
A51: x | B51: Checks
B53: Reported Financials — overall status (Block 1 + Block 2) | J53: ='Reported Financials'!J551 -> ALL OK
B54: Input financials — every number has a source | J54: ='Input financials'!M551 -> ALL OK
B55: Reformation & Profitability — overall status (Block 1 + Block 2) | J55: ='Reformation & Profitability'!J771 -> ALL OK
B57: Overall status | J57: =IF(COUNTIF(J53:J55,"ALL OK")=3,"ALL OK",3-COUNTIF(J53:J55,"ALL OK")&" to check") -> ALL OK
A59: x | B59: END

Sheet Reformation & Profitability
B3: =MID(CELL("filename",B3),FIND("]",CELL("filename",B3))+1,256) -> Reformation & Profitability
G6: Historicals
B7: (€ million) | C7: Rule | E7: 2022A | F7: =TEXT(VALUE(LEFT(E7, 4)) + 1, "####")&IF(VALUE(LEFT(E7, 4)) + 1 <= 2025, "A", "P") -> 2023A | G7: =TEXT(VALUE(LEFT(F7, 4)) + 1, "####")&IF(VALUE(LEFT(F7, 4)) + 1 <= 2025, "A", "P") -> 2024A | H7: =TEXT(VALUE(LEFT(G7, 4)) + 1, "####")&IF(VALUE(LEFT(G7, 4)) + 1 <= 2025, "A", "P") -> 2025A | J7: Where the number comes from / why (course slide)
B8: Fiscal year end date | E8: 44926 | F8: 45291 | G8: 45657 | H8: 46022
A10: x | B10: Reformulated Income Statement
B12: Net revenues | C12: R1 | F12: ='Reported Financials'!F12 -> 7176 | G12: ='Reported Financials'!G12 -> 7715 | H12: ='Reported Financials'!H12 -> 9935 | J12: Sales (IS). Slide 3: starting point of the roadmap
B13: Growth % | G13: =G12/F12-1 -> 0.075111483 | H13: =H12/G12-1 -> 0.28775113
B14: Change in inventories of finished and unfinished products | C14: R2 | F14: ='Reported Financials'!F15 -> 607 | G14: ='Reported Financials'!G15 -> 6 | H14: ='Reported Financials'!H15 -> 407 | J14: Note 10. Session 3 slide 6: production for inventory is part of the value of production
B15: Own work capitalised | C15: R2 | F15: ='Reported Financials'!F16 -> 89 | G15: ='Reported Financials'!G16 -> 126 | H15: ='Reported Financials'!H16 -> 114 | J15: Note 10. Session 3 slide 6: internal construction of assets
B16: Value of production | F16: =F12+F14+F15 -> 7872 | G16: =G12+G14+G15 -> 7847 | H16: =H12+H14+H15 -> 10456 | J16: Session 3 slide 6
B18: Raw materials, supplies and merchandise | C18: R3 | F18: ='Reported Financials'!F32 -> -2883 | G18: ='Reported Financials'!G32 -> -2435 | H18: ='Reported Financials'!H32 -> -3784 | J18: Note 12. External cost (Session 3 slide 6)
B19: Purchased services | C19: R3 | F19: ='Reported Financials'!F33 -> -1053 | G19: ='Reported Financials'!G33 -> -1258 | H19: ='Reported Financials'!H33 -> -1469 | J19: Note 12. External cost
B20: Other services purchased from third parties (note 15: maintenance, IT, distribution & advertising, administration, travel, insurance, audit/legal/consulting, rents, licences) | C20: R3 | F20: ='Reported Financials'!F48+'Reported Financials'!F49+'Reported Financials'!F50+'Reported Financials'!F52+'Reported Financials'!F53+'Reported Financials'!F54+'Reported Financials'!F56+'Reported Financials'!F58+'Reported Financials'!F60-'Reported Financials'!F92 -> -698 | G20: ='Reported Financials'!G48+'Reported Financials'!G49+'Reported Financials'!G50+'Reported Financials'!G52+'Reported Financials'!G53+'Reported Financials'!G54+'Reported Financials'!G56+'Reported Financials'!G58+'Reported Financials'!G60-'Reported Financials'!G92 -> -695 | H20: ='Reported Financials'!H48+'Reported Financials'!H49+'Reported Financials'!H50+'Reported Financials'!H52+'Reported Financials'!H53+'Reported Financials'!H54+'Reported Financials'!H56+'Reported Financials'!H58+'Reported Financials'!H60-'Reported Financials'!H92 -> -834 | J20: External cost = resources bought from third parties (Session 3 slide 6), classified component by component. Excl. acquisition transaction costs (unusual, R9)
B21: Rounding in note breakdowns (materials; inventory change and own work) | C21: R3 | F21: ='Reported Financials'!F34+'Reported Financials'!F17 -> 1 | G21: ='Reported Financials'!G34+'Reported Financials'!G17 -> 0 | H21: ='Reported Financials'!H34+'Reported Financials'!H17 -> 1 | J21: Reported Financials rounding lines of notes 10 and 12 (the components, not the face lines, are used above)
B22: Added value | F22: =F16+F18+F19+F20+F21 -> 3239 | G22: =G16+G18+G19+G20+G21 -> 3459 | H22: =H16+H18+H19+H20+H21 -> 4370 | J22: Session 3 slides 6–7: value of production − materials and services purchased from third parties
B23: Added value / value of production | F23: =F22/F16 -> 0.41145833 | G23: =G22/G16 -> 0.4408054 | H23: =H22/H16 -> 0.41794185
B25: Other operating income, recurring (not netted against external costs) | C25: R3 | F25: ='Reported Financials'!F20-'Reported Financials'!F27-'Reported Financials'!F98 -> 151 | G25: ='Reported Financials'!G20-'Reported Financials'!G27-'Reported Financials'!G98 -> 176 | H25: ='Reported Financials'!H20-'Reported Financials'!H27-'Reported Financials'!H98 -> 176 | J25: Note 11 excl. reversal of impairment and the estimated 2025 insurance refund (unusual, R9): refunds, grants, provision reversals, scrap, rentals, disposal gains. Not a reduction of purchases (slide 6), so shown after added value
B26: Other operating costs that are not purchases (provisions, warranties, receivable write-downs, disposal losses, other taxes, miscellaneous) | C26: R3 | F26: ='Reported Financials'!F55+'Reported Financials'!F57+'Reported Financials'!F59+'Reported Financials'!F61+'Reported Financials'!F62+'Reported Financials'!F63+'Reported Financials'!F64 -> -117 | G26: ='Reported Financials'!G55+'Reported Financials'!G57+'Reported Financials'!G59+'Reported Financials'!G61+'Reported Financials'!G62+'Reported Financials'!G63+'Reported Financials'!G64 -> -114 | H26: ='Reported Financials'!H55+'Reported Financials'!H57+'Reported Financials'!H59+'Reported Financials'!H61+'Reported Financials'!H62+'Reported Financials'!H63+'Reported Financials'!H64 -> -181 | J26: Note 15. Not purchases from suppliers (slide 6); provisions kept in operating costs before EBITDA (slide 8, option 1). Miscellaneous: content not disclosed
B27: Rounding difference to the printed EBIT | C27: R3 | F27: ='Reported Financials'!F68 -> 0 | G27: ='Reported Financials'!G68 -> -1 | H27: ='Reported Financials'!H68 -> -1 | J27: Reported Financials rounding line above EBIT (printed EBIT − sum of printed lines)
B28: Personnel costs, excl. restructuring costs | C28: R4 | F28: ='Reported Financials'!F35-'Reported Financials'!F96 -> -2046 | G28: ='Reported Financials'!G35-'Reported Financials'!G96 -> -1842 | H28: ='Reported Financials'!H35-'Reported Financials'!H96 -> -2307 | J28: Note 13. Internal cost (Session 3 slide 6). Restructuring special items removed (u7d): note 28 says structural measures are termination indemnities and partial retirement → personnel (assumption: the IS line is not disclosed)
B29: Incidental personnel costs (note 15) | C29: R4 | F29: ='Reported Financials'!F51 -> -74 | G29: ='Reported Financials'!G51 -> -76 | H29: ='Reported Financials'!H51 -> -97 | J29: Personnel-related, not a purchase of external resources: grouped with personnel (analyst classification)
B30: EBITDA | F30: =F22+F25+F26+F27+F28+F29 -> 1153 | G30: =G22+G25+G26+G27+G28+G29 -> 1602 | H30: =H22+H25+H26+H27+H28+H29 -> 1960 | J30: Session 3 slide 7: added value − personnel (and the other operating items above), before interest, D&A
B31: EBITDA margin | F31: =F30/F12 -> 0.16067447 | G31: =G30/G12 -> 0.20764744 | H31: =H30/H12 -> 0.19728234
B33: Net interest on pensions (reclassified from financial expenses; group total incl. discontinued operations) | C33: R4 | F33: ='Reported Financials'!F87 -> -10 | G33: ='Reported Financials'!G87 -> -12 | H33: ='Reported Financials'!H87 -> -5 | J33: Note 27. Operating because pensions are operating liabilities (slide 3; Session 4 slide 8), but an interest component: shown below EBITDA (slide 7: EBITDA is before interest)
B34: Depreciation and amortisation, recurring | C34: R5 | F34: ='Reported Financials'!F41-'Reported Financials'!F86 -> -302 | G34: ='Reported Financials'!G41-'Reported Financials'!G86 -> -284 | H34: ='Reported Financials'!H41-'Reported Financials'!H86 -> -389 | J34: Note 14 total excl. impairment losses (convention: unusual under the recurrence test, R9; Session 3 slide 8 option 2)
B35: of which amortisation from purchase price allocations | F35: ='Reported Financials'!F85 -> -47 | G35: ='Reported Financials'!G85 -> -102 | H35: ='Reported Financials'!H85 -> -139 | J35: Note 14 (memo, included above)
B36: Core operating income [A] | F36: =F30+F33+F34 -> 841 | G36: =G30+G33+G34 -> 1306 | H36: =H30+H33+H34 -> 1566 | J36: Slide 3: core operating income from sales
B37: Core operating margin (ROS) | F37: =F36/F12 -> 0.11719621 | G37: =G36/G12 -> 0.16928062 | H37: =H36/H12 -> 0.15762456
B39: Result from equity-accounted investments, excl. disposal gains | C39: R6 | F39: ='Reported Financials'!F66-'Reported Financials'!F89-'Reported Financials'!F90 -> 4 | G39: ='Reported Financials'!G66-'Reported Financials'!G89-'Reported Financials'!G90 -> -33 | H39: ='Reported Financials'!H66-'Reported Financials'!H89-'Reported Financials'!H90 -> 1 | J39: IS line excl. gains on sale of shares (unusual, R9). Slide 3: income from associates is non-core operating
B40: Other financial result, excl. remeasurement gains | C40: R6 | F40: ='Reported Financials'!F67-'Reported Financials'!F91 -> -11 | G40: ='Reported Financials'!G67-'Reported Financials'!G91 -> -9 | H40: ='Reported Financials'!H67-'Reported Financials'!H91 -> -22 | J40: IS line inside EBIT, less the blackned step-acquisition remeasurement gain (unusual, R9). Income on non-operating financial assets → non-core (slide 3); composition otherwise not disclosed
B41: Non-core operating income [B] | F41: =F39+F40 -> -7 | G41: =G39+G40 -> -42 | H41: =H39+H40 -> -21 | J41: Slide 3 [B]
B43: Operating income [A+B] | F43: =F36+F41 -> 834 | G43: =G36+G41 -> 1264 | H43: =H36+H41 -> 1545 | J43: Slide 3
B44: Operating margin | F44: =F43/F12 -> 0.11622074 | G44: =G43/G12 -> 0.16383668 | H44: =H43/H12 -> 0.15551082
B46: Financial income (interest income) | C46: R7 | F46: ='Reported Financials'!F71 -> 29 | G46: ='Reported Financials'!G71 -> 14 | H46: ='Reported Financials'!H71 -> 4 | J46: IS. Interest on cash and short-term financial assets (slide 3 [C])
B47: Financial expenses (interest expenses excl. pension interest) | C47: R7 | F47: ='Reported Financials'!F72-'Reported Financials'!F87 -> -101 | G47: ='Reported Financials'!G72-'Reported Financials'!G87 -> -104 | H47: ='Reported Financials'!H72-'Reported Financials'!H87 -> -111 | J47: IS less note 27 pension interest. Includes lease interest and IFRS 15 financing interest (not disclosed)
B48: Net financial expenses [C] | F48: =F46+F47 -> -72 | G48: =G46+G47 -> -90 | H48: =H46+H47 -> -107 | J48: Slide 3 and slide 4 (matched with the net financial position)
B50: Income before unusual items and taxes [A+B+C] | F50: =F43+F48 -> 762 | G50: =G43+G48 -> 1174 | H50: =H43+H48 -> 1438 | J50: Slide 3
B52: Unusual items (before tax) | C52: R9 | J52: Slides 15–26: criteria 1–5; examples on slide 21; ASICS layout on slide 27
B53: From the income statement:
B54: Reversal of impairment of assets | C54: R9 | F54: ='Reported Financials'!F27 -> 2 | G54: ='Reported Financials'!G27 -> 2 | H54: ='Reported Financials'!H27 -> 0 | J54: Note 11. Criterion: complex valuation / occasional (slides 21, 25)
B55: Impairment losses | C55: R9 | F55: ='Reported Financials'!F86 -> -6 | G55: ='Reported Financials'!G86 -> 0 | H55: ='Reported Financials'!H86 -> -17 | J55: Note 14. Occasional impairment (slide 21 '?'): not present in every year → unusual
B56: Gains on sale and fair-value measurement of shares in investments (Shriram 2023: 31 + 22; AIM 2025) | C56: R9 | F56: ='Reported Financials'!F89+'Reported Financials'!F90 -> 53 | G56: ='Reported Financials'!G89+'Reported Financials'!G90 -> 0 | H56: ='Reported Financials'!H89+'Reported Financials'!H90 -> 46 | J56: Management report. Criterion: infrequent (ASICS: gains on sales of investments)
B57: Fair-value remeasurement gains in other financial result (Shriram 2023; blackned step acquisition 2025) | C57: R9 | F57: ='Reported Financials'!F91 -> 5 | G57: ='Reported Financials'!G91 -> 0 | H57: ='Reported Financials'!H91 -> 15 | J57: AR2023 p.226 (Shriram 5); acquisition note, AR2025 p.214 (blackned 15). Criterion 5: fair-value remeasurement (slide 25, IFRS 3) and criterion 4: infrequent. Management also treats it as a special item
B58: Acquisition transaction costs (Loc Performance) | C58: R9 | F58: ='Reported Financials'!F92 -> 0 | G58: ='Reported Financials'!G92 -> -6 | H58: ='Reported Financials'!H92 -> 0 | J58: Management report special items, AR2025 p.55. Criterion 3/4: costs of a business combination, unusual in nature and infrequent (as AB InBev and Danone, slides 16–19)
B59: Restructuring costs (management special items) | C59: R9 | F59: ='Reported Financials'!F96 -> -1 | G59: ='Reported Financials'!G96 -> -2 | H59: ='Reported Financials'!H96 -> -7 | J59: Management report special items (AR2024 p.52, AR2025 p.55). Session 2 slide 31: restructuring charges are the named example of an account unusual for its full amount → overrides the recurrence test (I-46)
B60: Insurance refund for production losses at Murcia (estimated) | C60: R9 | F60: ='Reported Financials'!F98 -> 0 | G60: ='Reported Financials'!G98 -> 0 | H60: ='Reported Financials'!H98 -> 97 | J60: Note 11 (AR2025 p.219) and segment report (p.64: 'higher double-digit million euro amount'). Unusual: linked to a one-off natural disaster (slide 21). Amount estimated as refunds above the 2024 level (I-18)
B61: Discontinued operations, before tax | C61: R9 | F61: ='Reported Financials'!F100 -> -59 | G61: ='Reported Financials'!G100 -> -17 | H61: ='Reported Financials'!H100 -> -315 | J61: Note 8. Criterion 1: discontinued operations (slide 15, 26)
B62: Income taxes relating to prior years (earlier-period income taxes) | C62: R9 | F62: ='Reported Financials'!F93 -> 3 | G62: ='Reported Financials'!G93 -> -1 | H62: ='Reported Financials'!H93 -> -11 | J62: Tax note 16, AR2025 p.220 / AR2024 p.208. Slide 21, first example: taxes related to a past fiscal year do not respect the matching principle (ASICS shows refunded taxes as unusual, slide 27)
B63: From the statement of comprehensive income (before tax):
B64: Remeasurement of pensions | C64: R9 | F64: ='Reported Financials'!F102 -> 35 | G64: ='Reported Financials'!G102 -> 207 | H64: ='Reported Financials'!H102 -> 79 | J64: Note 26. Criterion 5: OCI / complex valuation (slides 22–25)
B65: Cash flow hedges | C65: R9 | F65: ='Reported Financials'!F104 -> -25 | G65: ='Reported Financials'!G104 -> 16 | H65: ='Reported Financials'!H104 -> 43 | J65: Note 26. Criterion 5 (ASICS: deferred gain on hedges)
B66: Currency translation differences | C66: R9 | F66: ='Reported Financials'!F105 -> 7 | G66: ='Reported Financials'!G105 -> 12 | H66: ='Reported Financials'!H105 -> -138 | J66: Note 26. Criterion 5 (ASICS: translation adjustments)
B67: OCI from equity-accounted investments | C67: R9 | F67: ='Reported Financials'!F103+'Reported Financials'!F106 -> -8 | G67: ='Reported Financials'!G103+'Reported Financials'!G106 -> 2 | H67: ='Reported Financials'!H103+'Reported Financials'!H106 -> 6 | J67: Note 26. Criterion 5
B68: Rounding: discontinued-operations note vs statement | C68: R9 | F68: ='Reported Financials'!F77-'Reported Financials'!F100-'Reported Financials'!F101 -> 0 | G68: ='Reported Financials'!G77-'Reported Financials'!G100-'Reported Financials'!G101 -> -1 | H68: ='Reported Financials'!H77-'Reported Financials'!H100-'Reported Financials'!H101 -> 1 | J68: Note 8 before-tax + tax vs printed earnings from discontinued operations. Not a criterion: keeps comprehensive income equal to the printed figure
B69: Rounding: OCI note vs statement | C69: R9 | F69: ='Reported Financials'!F119-SUM('Reported Financials'!F102:F106)-'Reported Financials'!F107 -> 0 | G69: ='Reported Financials'!G119-SUM('Reported Financials'!G102:G106)-'Reported Financials'!G107 -> 1 | H69: ='Reported Financials'!H119-SUM('Reported Financials'!H102:H106)-'Reported Financials'!H107 -> -1 | J69: Note 26 before-tax + tax vs printed OCI after taxes
B70: Total unusual items | F70: =SUM(F54:F69) -> 6 | G70: =SUM(G54:G69) -> 213 | H70: =SUM(H54:H69) -> -202
B71: Unusual items / net revenues | F71: =F70/F12 -> 0.0008361204 | G71: =G70/G12 -> 0.027608555 | H71: =H70/H12 -> -0.020332159
B73: Earnings before taxes (comprehensive) | F73: =F50+F70 -> 768 | G73: =G50+G70 -> 1387 | H73: =H50+H70 -> 1236 | J73: Slide 3 / ASICS slide 27
B75: Income taxes (continuing operations), excl. earlier-period taxes | C75: R10 | F75: ='Reported Financials'!F74-'Reported Financials'!F93 -> -188 | G75: ='Reported Financials'!G74-'Reported Financials'!G93 -> -327 | H75: ='Reported Financials'!H74-'Reported Financials'!H93 -> -385 | J75: IS less earlier-period taxes (moved to unusual items, R9)
B76: Income taxes on discontinued operations | C76: R10 | F76: ='Reported Financials'!F101 -> 15 | G76: ='Reported Financials'!G101 -> -14 | H76: ='Reported Financials'!H101 -> -27 | J76: Note 8
B77: Taxes on OCI items | C77: R10 | F77: ='Reported Financials'!F107 -> 2 | G77: ='Reported Financials'!G107 -> -47 | H77: ='Reported Financials'!H107 -> -38 | J77: Note 26 (ASICS: taxes on OCI items)
B78: Income taxes | C78: R10 | F78: =F75+F76+F77 -> -171 | G78: =G75+G76+G77 -> -388 | H78: =H75+H76+H77 -> -450
B79: Tax rate on earnings before taxes | F79: =-F78/F73 -> 0.22265625 | G79: =-G78/G73 -> 0.27974045 | H79: =-H78/H73 -> 0.36407767
B81: Comprehensive income | F81: =F73+F78 -> 597 | G81: =G73+G78 -> 999 | H81: =H73+H78 -> 786 | J81: Slide 3: bottom line = net income (comprehensive income)
B82: of which non-controlling interests | F82: ='Reported Financials'!F121 -> 39 | G82: ='Reported Financials'!G121 -> 98 | H82: ='Reported Financials'!H121 -> 150 | J82: Statement of comprehensive income
B83: of which Rheinmetall AG shareholders | F83: =F81-F82 -> 558 | G83: =G81-G82 -> 901 | H83: =H81-H82 -> 636
B85: Memo: net income (earnings after taxes, as reported) | F85: ='Reported Financials'!F78 -> 586 | G85: ='Reported Financials'!G78 -> 808 | H85: ='Reported Financials'!H78 -> 835 | J85: IS
B87: Recurrence test for matching-principle, infrequent and '?' items (R9; Session 2 slides 21, 26) | C87: R9 | J87: Rule: an item that recurs with the same sign in all three years is part of normal operations → stays in [A]/[B]; otherwise unusual (slide 26: unusual items are volatile in amount and sign)
B88: Reversal of provisions (n.11) | C88: R9 | F88: ='Reported Financials'!F23 -> 53 | G88: ='Reported Financials'!G23 -> 55 | H88: ='Reported Financials'!H23 -> 44 | J88: =IF(OR(AND(F88>0,G88>0,H88>0),AND(F88<0,G88<0,H88<0)),"Recurring: same sign in all 3 years → stays in [A]/[B]","Unusual: not present with the same sign in all 3 years → R9")&"" -> Recurring: same sign in all 3 years → stays in [A]/[B]
B89: Net result from disposals of non-current assets (gains n.11 + losses n.15) | C89: R9 | F89: ='Reported Financials'!F26+'Reported Financials'!F61 -> -8 | G89: ='Reported Financials'!G26+'Reported Financials'!G61 -> -19 | H89: ='Reported Financials'!H26+'Reported Financials'!H61 -> -8 | J89: =IF(OR(AND(F89>0,G89>0,H89>0),AND(F89<0,G89<0,H89<0)),"Recurring: same sign in all 3 years → stays in [A]/[B]","Unusual: not present with the same sign in all 3 years → R9")&"" -> Recurring: same sign in all 3 years → stays in [A]/[B]
B90: Write-downs of receivables (n.15) | C90: R9 | F90: ='Reported Financials'!F57 -> -7 | G90: ='Reported Financials'!G57 -> -2 | H90: ='Reported Financials'!H57 -> -33 | J90: =IF(OR(AND(F90>0,G90>0,H90>0),AND(F90<0,G90<0,H90<0)),"Recurring: same sign in all 3 years → stays in [A]/[B]","Unusual: not present with the same sign in all 3 years → R9")&" 2025 jump flagged in the trend analysis" -> Recurring: same sign in all 3 years → stays in [A]/[B] 2025 jump flagged in the trend analysis
B91: Impairment net of reversals (n.14, n.11) | C91: R9 | F91: ='Reported Financials'!F86+'Reported Financials'!F27 -> -4 | G91: ='Reported Financials'!G86+'Reported Financials'!G27 -> 2 | H91: ='Reported Financials'!H86+'Reported Financials'!H27 -> -17 | J91: =IF(OR(AND(F91>0,G91>0,H91>0),AND(F91<0,G91<0,H91<0)),"Recurring: same sign in all 3 years → stays in [A]/[B]","Unusual: not present with the same sign in all 3 years → R9")&"" -> Unusual: not present with the same sign in all 3 years → R9
B92: Earlier-period income taxes (n.16) | C92: R9 | F92: ='Reported Financials'!F93 -> 3 | G92: ='Reported Financials'!G93 -> -1 | H92: ='Reported Financials'!H93 -> -11 | J92: =IF(OR(AND(F92>0,G92>0,H92>0),AND(F92<0,G92<0,H92<0)),"Recurring: same sign in all 3 years → stays in [A]/[B]","Unusual: not present with the same sign in all 3 years → R9")&"" -> Unusual: not present with the same sign in all 3 years → R9
B93: Management special items: restructuring | C93: R9 | F93: ='Reported Financials'!F96 -> -1 | G93: ='Reported Financials'!G96 -> -2 | H93: ='Reported Financials'!H96 -> -7 | J93: Override: recurring by the test, but Session 2 slide 31 names restructuring charges as unusual for the full amount → moved to u7d (I-46)
B94: Management special items: others | C94: R9 | F94: ='Reported Financials'!F97 -> -6 | G94: ='Reported Financials'!G97 -> 11 | H94: ='Reported Financials'!H97 -> -1 | J94: =IF(OR(AND(F94>0,G94>0,H94>0),AND(F94<0,G94<0,H94<0)),"Recurring: same sign in all 3 years → stays in [A]/[B]","Unusual: not present with the same sign in all 3 years → R9")&" — but line and content not disclosed: cannot be moved; logged (I-26)" -> Unusual: not present with the same sign in all 3 years → R9 — but line and content not disclosed: cannot be moved; logged (I-26)
B96: Unusual changes of usual items — trend analysis (Session 2, slides 30–32) | C96: R12 | J96: Slide 31: category 2 = unusual portion of a usual line → trend analysis, not reclassification. Slide 32: growth rates and CAGR. 2024 vs 2023 not like-for-like (I-01)
B97: Growth % — Net revenues | C97: R12 | G97: =G12/F12-1 -> 0.075111483 | H97: =H12/G12-1 -> 0.28775113 | J97: ="CAGR 2023–25: "&TEXT((H12/F12)^(1/2)-1,"0.0%")&" | % of net revenues: "&TEXT(F12/F12,"0.0%")&" → "&TEXT(G12/G12,"0.0%")&" → "&TEXT(H12/H12,"0.0%") -> CAGR 2023–25: 17.7% | % of net revenues: 100.0% → 100.0% → 100.0%
B98: Growth % — Value of production | C98: R12 | G98: =G16/F16-1 -> -0.003175813 | H98: =H16/G16-1 -> 0.33248375 | J98: ="CAGR 2023–25: "&TEXT((H16/F16)^(1/2)-1,"0.0%")&" | % of net revenues: "&TEXT(F16/F12,"0.0%")&" → "&TEXT(G16/G12,"0.0%")&" → "&TEXT(H16/H12,"0.0%") -> CAGR 2023–25: 15.2% | % of net revenues: 109.7% → 101.7% → 105.2%
B99: Growth % — Raw materials, supplies and merchandise | C99: R12 | G99: =G18/F18-1 -> -0.15539369 | H99: =H18/G18-1 -> 0.55400411 | J99: ="CAGR 2023–25: "&TEXT((H18/F18)^(1/2)-1,"0.0%")&" | % of net revenues: "&TEXT(F18/F12,"0.0%")&" → "&TEXT(G18/G12,"0.0%")&" → "&TEXT(H18/H12,"0.0%") -> CAGR 2023–25: 14.6% | % of net revenues: -40.2% → -31.6% → -38.1%
B100: Growth % — Purchased services | C100: R12 | G100: =G19/F19-1 -> 0.19468186 | H100: =H19/G19-1 -> 0.16772655 | J100: ="CAGR 2023–25: "&TEXT((H19/F19)^(1/2)-1,"0.0%")&" | % of net revenues: "&TEXT(F19/F12,"0.0%")&" → "&TEXT(G19/G12,"0.0%")&" → "&TEXT(H19/H12,"0.0%") -> CAGR 2023–25: 18.1% | % of net revenues: -14.7% → -16.3% → -14.8%
B101: Growth % — Other services purchased | C101: R12 | G101: =G20/F20-1 -> -0.0042979943 | H101: =H20/G20-1 -> 0.2 | J101: ="CAGR 2023–25: "&TEXT((H20/F20)^(1/2)-1,"0.0%")&" | % of net revenues: "&TEXT(F20/F12,"0.0%")&" → "&TEXT(G20/G12,"0.0%")&" → "&TEXT(H20/H12,"0.0%") -> CAGR 2023–25: 9.3% | % of net revenues: -9.7% → -9.0% → -8.4%
B102: Growth % — Other operating costs, not purchases | C102: R12 | G102: =G26/F26-1 -> -0.025641026 | H102: =H26/G26-1 -> 0.5877193 | J102: ="CAGR 2023–25: "&TEXT((H26/F26)^(1/2)-1,"0.0%")&" | % of net revenues: "&TEXT(F26/F12,"0.0%")&" → "&TEXT(G26/G12,"0.0%")&" → "&TEXT(H26/H12,"0.0%") -> CAGR 2023–25: 24.4% | % of net revenues: -1.6% → -1.5% → -1.8%
B103: Growth % — Other operating income, recurring | C103: R12 | G103: =G25/F25-1 -> 0.16556291 | H103: =H25/G25-1 -> 0 | J103: ="CAGR 2023–25: "&TEXT((H25/F25)^(1/2)-1,"0.0%")&" | % of net revenues: "&TEXT(F25/F12,"0.0%")&" → "&TEXT(G25/G12,"0.0%")&" → "&TEXT(H25/H12,"0.0%") -> CAGR 2023–25: 8.0% | % of net revenues: 2.1% → 2.3% → 1.8%
B104: Growth % — Personnel costs | C104: R12 | G104: =G28/F28-1 -> -0.099706745 | H104: =H28/G28-1 -> 0.252443 | J104: ="CAGR 2023–25: "&TEXT((H28/F28)^(1/2)-1,"0.0%")&" | % of net revenues: "&TEXT(F28/F12,"0.0%")&" → "&TEXT(G28/G12,"0.0%")&" → "&TEXT(H28/H12,"0.0%") -> CAGR 2023–25: 6.2% | % of net revenues: -28.5% → -23.9% → -23.2%
B105: Growth % — Depreciation and amortisation, recurring | C105: R12 | G105: =G34/F34-1 -> -0.059602649 | H105: =H34/G34-1 -> 0.36971831 | J105: ="CAGR 2023–25: "&TEXT((H34/F34)^(1/2)-1,"0.0%")&" | % of net revenues: "&TEXT(F34/F12,"0.0%")&" → "&TEXT(G34/G12,"0.0%")&" → "&TEXT(H34/H12,"0.0%") -> CAGR 2023–25: 13.5% | % of net revenues: -4.2% → -3.7% → -3.9%
B106: Growth % — EBITDA | C106: R12 | G106: =G30/F30-1 -> 0.38941891 | H106: =H30/G30-1 -> 0.22347066 | J106: ="CAGR 2023–25: "&TEXT((H30/F30)^(1/2)-1,"0.0%")&" | % of net revenues: "&TEXT(F30/F12,"0.0%")&" → "&TEXT(G30/G12,"0.0%")&" → "&TEXT(H30/H12,"0.0%") -> CAGR 2023–25: 30.4% | % of net revenues: 16.1% → 20.8% → 19.7%
B107: Growth % — Core operating income [A] | C107: R12 | G107: =G36/F36-1 -> 0.5529132 | H107: =H36/G36-1 -> 0.19908116 | J107: ="CAGR 2023–25: "&TEXT((H36/F36)^(1/2)-1,"0.0%")&" | % of net revenues: "&TEXT(F36/F12,"0.0%")&" → "&TEXT(G36/G12,"0.0%")&" → "&TEXT(H36/H12,"0.0%") -> CAGR 2023–25: 36.5% | % of net revenues: 11.7% → 16.9% → 15.8%
B108: Growth % — net revenues on a comparable perimeter (2023 excl. civilian business) | C108: R12 | G108: =G12/(F12-'Reported Financials'!F94)-1 -> 0.51422964 | J108: 2023 as reported (AR2024, not restated) still contains the civilian business: external sales 2,081 (AR2024 p.193). 2024 is restated without it
B109: R&D expenses / net revenues (Abbott example, slide 30) | C109: R12 | F109: =-'Reported Financials'!F108/F12 -> 0.030239688 | G109: =-'Reported Financials'!G108/G12 -> 0.012832145 | H109: =-'Reported Financials'!H108/H12 -> 0.010568697 | J109: 2023 includes the civilian business (R&D-intensive): the 2023→2024 fall is mainly a perimeter effect, not a red flag. Compare 2024→2025 only
B110: 2025 refunds of 118 (21, 5) are mainly insurance payments for production losses at Murcia: the estimated unusual portion (97) is moved to u7e (I-18). 2025 write-downs of receivables of 33 (2, 7): flagged, kept in [A] (slide 31, category 2, no unusual portion disclosed). | C110: R12
A112: x | B112: Operating Cost Structure — three reformulations (Session 3)
B114: 1. Income statement by function (Session 3, slides 3–5) | C114: C1 | J114: Needs cost of sales, selling, G&A and R&D costs
B115: Net revenues | C115: C1 | F115: =F12 -> 7176 | G115: =G12 -> 7715 | H115: =H12 -> 9935
B116: Cost of sales | C116: C1 | F116: n.d. | G116: n.d. | H116: n.d. | J116: Not reliably determinable: presented by nature; direct labour and factory overhead are not disclosed (test below). No allocation is made (slide 4)
B117: Gross profit | C117: C1 | F117: n.d. | G117: n.d. | H117: n.d.
B118: Selling costs | C118: C1 | F118: n.d. | G118: n.d. | H118: n.d.
B119: General & administrative costs | C119: C1 | F119: n.d. | G119: n.d. | H119: n.d.
B120: R&D costs | C120: C1 | F120: n.d. | G120: n.d. | H120: n.d.
B121: Availability test for cost of sales (C1, slide 4 — manufacturing company) | C121: C1
B122: Presentation of the income statement | C122: C1 | J122: By nature: materials, personnel, D&A, other operating expenses (IS, AR2025 p.199)
...

Sheet Reported Financials
B3: =MID(CELL("filename",B3),FIND("]",CELL("filename",B3))+1,256) -> Reported Financials
G6: Historicals
B7: (€ million) | C7: Note | E7: 2022A | F7: =TEXT(VALUE(LEFT(E7, 4)) + 1, "####")&IF(VALUE(LEFT(E7, 4)) + 1 <= 2025, "A", "P") -> 2023A | G7: =TEXT(VALUE(LEFT(F7, 4)) + 1, "####")&IF(VALUE(LEFT(F7, 4)) + 1 <= 2025, "A", "P") -> 2024A | H7: =TEXT(VALUE(LEFT(G7, 4)) + 1, "####")&IF(VALUE(LEFT(G7, 4)) + 1 <= 2025, "A", "P") -> 2025A | J7: Comment
B8: Fiscal year end date | E8: 44926 | F8: 45291 | G8: 45657 | H8: 46022
A10: x | B10: Income Statement
B12: Sales | C12: 9 | F12: 7176 | G12: 7715 | H12: 9935 | J12: 2024 restated in AR2025 (civilian business → discontinued); 2023 from AR2024, not restated
B13: Growth % | G13: =G12/F12-1 -> 0.075111483 | H13: =H12/G12-1 -> 0.28775113 | J13: 2024 vs 2023 not like-for-like
B14: Changes in inventories and work performed by the enterprise and capitalized | C14: 10 | F14: =SUM(F15:F17) -> 696 | G14: =SUM(G15:G17) -> 132 | H14: =SUM(H15:H17) -> 521
B15: Increase in inventory of finished and unfinished products | C15: 10 | F15: 607 | G15: 6 | H15: 407
B16: Other work performed by the enterprise and capitalized | C16: 10 | F16: 89 | G16: 126 | H16: 114
B17: Rounding / undisclosed difference | F17: =F236-(SUM(F15:F16)) -> 0 | G17: =G236-(SUM(G15:G16)) -> 0 | H17: =H236-(SUM(H15:H16)) -> 0 | J17: Printed figure − sum of the printed lines above; ≤ tolerance = rounding, larger = undisclosed item (log it)
B18: Total operating performance | F18: =F12+F14 -> 7872 | G18: =G12+G14 -> 7847 | H18: =H12+H14 -> 10456
B20: Other operating income | C20: 11 | F20: =SUM(F21:F29) -> 153 | G20: =SUM(G21:G29) -> 178 | H20: =SUM(H21:H29) -> 273
B21: Refunds | C21: 11 | F21: 5 | G21: 21 | H21: 118 | J21: 2025: mainly insurance payments for production losses (n.11)
B22: Government grants | C22: 11 | F22: 16 | G22: 26 | H22: 48
B23: Reversal of provisions | C23: 11 | F23: 53 | G23: 55 | H23: 44
B24: Residual/scrap disposal | C24: 11 | F24: 6 | G24: 7 | H24: 12
B25: Sundry rental agreements and leases | C25: 11 | F25: 8 | G25: 5 | H25: 4
B26: Disposal of fixed assets/divestments | C26: 11 | F26: 0 | G26: 2 | H26: 1
B27: Reversal of assets (excl. financial assets) | C27: 11 | F27: 2 | G27: 2 | H27: 0
B28: Miscellaneous operating income | C28: 11 | F28: 64 | G28: 60 | H28: 47
B29: Rounding / undisclosed difference | F29: =F238-(SUM(F21:F28)) -> -1 | G29: =G238-(SUM(G21:G28)) -> 0 | H29: =H238-(SUM(H21:H28)) -> -1 | J29: Printed figure − sum of the printed lines above; ≤ tolerance = rounding, larger = undisclosed item (log it)
B31: Cost of materials | C31: 12 | F31: =SUM(F32:F34) -> -3935 | G31: =SUM(G32:G34) -> -3693 | H31: =SUM(H32:H34) -> -5252 | J31: Printed without brackets as an expense
B32: Cost of raw materials, supplies and merchandise purchased | C32: 12 | F32: -2883 | G32: -2435 | H32: -3784
B33: Cost of services purchased | C33: 12 | F33: -1053 | G33: -1258 | H33: -1469
B34: Rounding / undisclosed difference | F34: =F239-(SUM(F32:F33)) -> 1 | G34: =G239-(SUM(G32:G33)) -> 0 | H34: =H239-(SUM(H32:H33)) -> 1 | J34: Printed figure − sum of the printed lines above; ≤ tolerance = rounding, larger = undisclosed item (log it)
B35: Personnel costs | C35: 13 | F35: =SUM(F36:F40) -> -2047 | G35: =SUM(G36:G40) -> -1844 | H35: =SUM(H36:H40) -> -2314
B36: Wages and salaries | C36: 13 | F36: -1711 | G36: -1533 | H36: -1907
B37: Social security and related employee benefits | C37: 13 | F37: -205 | G37: -194 | H37: -264
B38: Pension expenses | C38: 13 | F38: -115 | G38: -104 | H38: -128
B39: Expenses for redundancy plans, termination indemnities, partial retirement | C39: 13 | F39: -16 | G39: -13 | H39: -16
B40: Rounding / undisclosed difference | F40: =F240-(SUM(F36:F39)) -> 0 | G40: =G240-(SUM(G36:G39)) -> 0 | H40: =H240-(SUM(H36:H39)) -> 1 | J40: Printed figure − sum of the printed lines above; ≤ tolerance = rounding, larger = undisclosed item (log it)
B41: Amortization, depreciation and impairment | C41: 14 | F41: =SUM(F42:F45) -> -308 | G41: =SUM(G42:G45) -> -284 | H41: =SUM(H42:H45) -> -406
B42: Other intangible assets | C42: 14 | F42: -87 | G42: -132 | H42: -185
B43: Right-of-use assets | C43: 14 | F43: -47 | G43: -41 | H43: -51
B44: Property, plant and equipment and investment property | C44: 14 | F44: -174 | G44: -110 | H44: -169
B45: Rounding / undisclosed difference | F45: =F241-(SUM(F42:F44)) -> 0 | G45: =G241-(SUM(G42:G44)) -> -1 | H45: =H241-(SUM(H42:H44)) -> -1 | J45: Printed figure − sum of the printed lines above; ≤ tolerance = rounding, larger = undisclosed item (log it)
B46: % of sales | F46: =-F41/F12 -> 0.042920847 | G46: =-G41/G12 -> 0.036811406 | H46: =-H41/H12 -> 0.040865627
B47: Other operating expenses | C47: 15 | F47: =SUM(F48:F64) -> -889 | G47: =SUM(G48:G64) -> -891 | H47: =SUM(H48:H64) -> -1112
B48: Operating costs and maintenance | C48: 15 | F48: -175 | G48: -179 | H48: -252
B49: IT costs | C49: 15 | F49: -159 | G49: -163 | H49: -159
B50: Distribution and advertising costs | C50: 15 | F50: -117 | G50: -110 | H50: -133
B51: Incidental personnel costs | C51: 15 | F51: -74 | G51: -76 | H51: -97
B52: General administrative expenses | C52: 15 | F52: -54 | G52: -65 | H52: -93
B53: Travel expenses | C53: 15 | F53: -58 | G53: -57 | H53: -65
B54: Insurances | C54: 15 | F54: -43 | G54: -42 | H54: -52
B55: Changes in / additions to other provisions | C55: 15 | F55: -4 | G55: -14 | H55: -47
B56: Audit, legal and consultancy fees | C56: 15 | F56: -50 | G56: -50 | H56: -41
B57: Write-downs of receivables | C57: 15 | F57: -7 | G57: -2 | H57: -33
B58: Rents, leases and ancillary costs | C58: 15 | F58: -31 | G58: -21 | H58: -29
B59: Warranties | C59: 15 | F59: -13 | G59: -15 | H59: -20
... B63: Miscellaneous operating expenses | C63: 15 | F63: -75 | G63: -54 | H63: -62
B64: Rounding / undisclosed difference | F64: =F242-(SUM(F48:F63)) -> 0 | G64: =G242-(SUM(G48:G63)) -> -1 | H64: =H242-(SUM(H48:H63)) -> -1 | J64: Printed figure − sum of the printed lines above; ≤ tolerance = rounding, larger = undisclosed item (log it)
B66: Result from investments accounted for using the equity method | C66: 22 | F66: 57 | G66: -33 | H66: 47 | J66: AR2023 text shows '157' = footnote 1 + 57
B67: Other financial result | F67: -6 | G67: -9 | H67: -7 | J67: Reported inside EBIT; no note breakdown found
B68: Rounding difference to the printed subtotal | F68: =F243-(F18+F20+F31+F35+F41+F47+F66+F67) -> 0 | G68: =G243-(G18+G20+G31+G35+G41+G47+G66+G67) -> -1 | H68: =H243-(H18+H20+H31+H35+H41+H47+H66+H67) -> -1 | J68: Printed figure − sum of the printed lines above; ≤ tolerance = rounding, larger = undisclosed item (log it)
B69: Earnings before interest and taxes (EBIT) | F69: =F18+F20+F31+F35+F41+F47+F66+F67+F68 -> 897 | G69: =G18+G20+G31+G35+G41+G47+G66+G67+G68 -> 1270 | H69: =H18+H20+H31+H35+H41+H47+H66+H67+H68 -> 1684
B70: EBIT margin | F70: =F69/F12 -> 0.125 | G70: =G69/G12 -> 0.16461439 | H70: =H69/H12 -> 0.16950176
B71: Interest income | F71: 29 | G71: 14 | H71: 4
B72: Interest expenses | F72: -111 | G72: -116 | H72: -116 | J72: Includes IFRS 15 financing-component interest on customer advances; amount not disclosed (AR2025 p.56)
B73: Earnings before taxes (EBT) | F73: =F69+F71+F72 -> 815 | G73: =G69+G71+G72 -> 1168 | H73: =H69+H71+H72 -> 1572
B74: Income taxes | C74: 16 | F74: -185 | G74: -328 | H74: -396
B75: Effective tax rate | F75: =-F74/F73 -> 0.22699387 | G75: =-G74/G73 -> 0.28082192 | H75: =-H74/H73 -> 0.2519084
B76: Earnings from continuing operations | F76: =F73+F74 -> 630 | G76: =G73+G74 -> 840 | H76: =H73+H74 -> 1176
B77: Earnings from discontinued operations | C77: 8 | F77: -44 | G77: -32 | H77: -341 | J77: 2025: civilian business (incl. impairment 350); 2023–24: Pistons
B78: Earnings after taxes | F78: =F76+F77 -> 586 | G78: =G76+G77 -> 808 | H78: =H76+H77 -> 835
B79: Non-controlling interests | F79: 51 | G79: 91 | H79: 139
B80: Rheinmetall AG shareholders | F80: =F78-F79 -> 535 | G80: =G78-G79 -> 717 | H80: =H78-H79 -> 696
B81: Profit margin | F81: =F78/F12 -> 0.081661093 | G81: =G78/G12 -> 0.10473104 | H81: =H78/H12 -> 0.084046301
A83: x | B83: Additional information from the notes (included in the lines above)
B85: Amortisation from purchase price allocations (PPA) | C85: 14 | F85: -47 | G85: -102 | H85: -139 | J85: Included in amortization, depreciation and impairment
B86: Impairment losses | C86: 14 | F86: -6 | G86: 0 | H86: -17 | J86: Included in amortization, depreciation and impairment
B87: Net interest on pensions (interest cost − interest income on plan assets) | C87: 27 | F87: -10 | G87: -12 | H87: -5 | J87: Included in interest expenses; group total incl. discontinued ops
B88: Interest expenses from lease liabilities | C88: 19 | F88: -10 | G88: -10 | H88: -14 | J88: Included in interest expenses
B89: Shriram Pistons & Rings: gain on sale of share packages (31) + initial fair-value measurement of the remaining shares (22) | F89: 53 | G89: 0 | H89: 0 | J89: Included in the equity-method result. Total Shriram effect 2023 = 69 (AR2023 p.226): 31 + 22 here, 5 FV in other financial result, 10 at-equity share of profit, 1 dividend
B90: Gain on sale of AIM shares (not adjusted by the company) | F90: 0 | G90: 0 | H90: 46 | J90: Included in the equity-method result (management report)
B91: Fair-value remeasurement gains in other financial result (2023: Shriram shares; 2025: previously held 40% interest in blackned, IFRS 3) | F91: 5 | G91: 0 | H91: 15 | J91: Included in the other financial result. 2023: subsequent fair-value measurement of the Shriram shares (AR2023 p.226); 2024: none disclosed
B92: Transaction costs for the acquisition of Loc Performance (management special item) | F92: 0 | G92: -6 | H92: 0 | J92: Included in operating costs (other operating expenses). Amount from AR2024 p.51 and AR2025 p.55 (Vehicle Systems, corporate transactions); none in 2023 and 2025
B93: Earlier-period income taxes (included in income taxes) | C93: 16 | F93: 3 | G93: -1 | H93: -11 | J93: Composition of income taxes. 2023 = income of 3 (AR2024, printed '(3)'); 2024 restated in AR2025
B94: Civilian business (Power Systems segment): external sales, as originally reported | F94: 2081 | G94: 2032 | J94: Memo, not added into any total. Inside 2023 sales (AR2024 not restated); in 2024 the business is in discontinued operations (AR2025)
B95: Civilian business (Power Systems segment): EBIT, as originally reported | F95: 129 | G95: 75 | J95: Memo, not added into any total. Segment EBIT, not reformulated
B96: Management special items: restructuring | F96: -1 | G96: -2 | H96: -7 | J96: Line of the income statement that contains it is not disclosed
B97: Management special items: others | F97: -6 | G97: 11 | H97: -1 | J97: Content and line not disclosed
B98: Insurance refund for production losses (Murcia), estimated unusual portion of refunds | C98: 11 | F98: 0 | G98: 0 | H98: 97 | J98: Estimate = 2025 refunds above the 2024 level (118 − 21 = 97), consistent with management's 'higher double-digit million euro amount'. Included in refunds (n.11); memo, not added into any total
B99: Provisions for structural measures (restructuring), in other provisions | C99: 28 | E99: 55 | F99: 46 | G99: 52 | H99: 25 | J99: Termination indemnities and partial-retirement obligations (note 28). Included in other current and non-current provisions; memo, not added into any total
B100: Discontinued operations: earnings before taxes | C100: 8 | F100: -59 | G100: -17 | H100: -315 | J100: 2024–25: civilian business + small-bore pistons (two tables, AR2025 p.215–216); 2023: pistons
B101: Discontinued operations: income taxes | C101: 8 | F101: 15 | G101: -14 | H101: -27 | J101: Pre-tax + taxes = earnings from discontinued operations
B102: OCI before tax: remeasurement of net defined benefit liability from pensions | C102: 26 | F102: 35 | G102: 207 | H102: 79
B103: OCI before tax: equity-method investments (not reclassified) | C103: 26 | F103: 0 | G103: -2 | H103: 0
B104: OCI before tax: change in value of derivatives (cash flow hedges) | C104: 26 | F104: -25 | G104: 16 | H104: 43
B105: OCI before tax: currency translation difference | C105: 26 | F105: 7 | G105: 12 | H105: -138
B106: OCI before tax: equity-method investments (reclassified) | C106: 26 | F106: -8 | G106: 4 | H106: 6
B107: Tax effect on other comprehensive income | C107: 26 | F107: 2 | G107: -47 | H107: -38 | J107: Printed total of the tax-effect column
B108: Research and development costs recognised as expenses | C108: 18 | F108: -217 | G108: -99 | H108: -105 | J108: Included in the cost lines above (by nature). 2023 = AR2024 n.18 (old perimeter); 2024–25 = AR2025 management report p.31
B109: Statutory tax rate | C109: 16 | F109: 0.3 | G109: 0.3 | H109: 0.3 | J109: Corporation tax 15% + solidarity surcharge 5.5% + trade tax 15%
A111: x | B111: Statement of Comprehensive Income
B113: Remeasurement of net defined benefit liability from pensions | F113: 30 | G113: 165 | H113: 52
B114: Other comprehensive income from investments accounted for using the equity method (not reclassified) | F114: 0 | G114: -2 | H114: 0
B115: Change in value of derivative financial instruments (cash flow hedge) | F115: -19 | G115: 11 | H115: 31
B116: Currency translation difference | F116: 7 | G116: 12 | H116: -138
...

Sheet Input financials
B3: =MID(CELL("filename",B3),FIND("]",CELL("filename",B3))+1,256) -> Input financials
G6: Source (report, printed page)
B7: (€ million) | C7: Note | E7: 2022A | F7: =TEXT(VALUE(LEFT(E7, 4)) + 1, "####")&IF(VALUE(LEFT(E7, 4)) + 1 <= 2025, "A", "P") -> 2023A | G7: =TEXT(VALUE(LEFT(F7, 4)) + 1, "####")&IF(VALUE(LEFT(F7, 4)) + 1 <= 2025, "A", "P") -> 2024A | H7: =TEXT(VALUE(LEFT(G7, 4)) + 1, "####")&IF(VALUE(LEFT(G7, 4)) + 1 <= 2025, "A", "P") -> 2025A | J7: Caption exactly as printed | K7: Status | M7: Number ↔ source
B8: Fiscal year end date | E8: 44926 | F8: 45291 | G8: 45657 | H8: 46022
A10: x | B10: Income Statement
B12: Sales | C12: 9 | F12: AR2024 p.188 | G12: AR2025 p.199 | H12: AR2025 p.199 | J12: Sales | K12: found; 2024 restated | M12: =IF(COUNT('Reported Financials'!E12:H12)=0,"",IF(SUMPRODUCT(--ISNUMBER('Reported Financials'!E12:H12),--(E12:H12=""))=0,"OK","source missing")) -> OK
B13: Growth % | G13: formula | H13: formula | K13: derived (subtotal)
B14: Changes in inventories and work performed by the enterprise and capitalized | C14: 10 | F14: sum of lines below | G14: sum of lines below | H14: sum of lines below | J14: Changes in inventories and work performed by the enterprise and capitalized | K14: derived (sum of note lines); printed figure in Checks | M14: =IF(COUNT('Reported Financials'!E14:H14)=0,"",IF(SUMPRODUCT(--ISNUMBER('Reported Financials'!E14:H14),--(E14:H14=""))=0,"OK","source missing")) -> OK
B15: Increase in inventory of finished and unfinished products | C15: 10 | F15: AR2024 p.206 | G15: AR2025 p.218 | H15: AR2025 p.218 | J15: Increase in inventory of finished and unfinished products | K15: found | M15: =IF(COUNT('Reported Financials'!E15:H15)=0,"",IF(SUMPRODUCT(--ISNUMBER('Reported Financials'!E15:H15),--(E15:H15=""))=0,"OK","source missing")) -> OK
B16: Other work performed by the enterprise and capitalized | C16: 10 | F16: AR2024 p.206 | G16: AR2025 p.218 | H16: AR2025 p.218 | J16: Other work performed by the enterprise and capitalized | K16: found | M16: =IF(COUNT('Reported Financials'!E16:H16)=0,"",IF(SUMPRODUCT(--ISNUMBER('Reported Financials'!E16:H16),--(E16:H16=""))=0,"OK","source missing")) -> OK
B17: Rounding / undisclosed difference | F17: formula | G17: formula | H17: formula | K17: derived (rounding / undisclosed difference)
B18: Total operating performance | F18: formula | G18: formula | H18: formula | K18: derived (subtotal)
B20: Other operating income | C20: 11 | F20: sum of lines below | G20: sum of lines below | H20: sum of lines below | J20: Other operating income | K20: derived (sum of note lines); printed figure in Checks | M20: =IF(COUNT('Reported Financials'!E20:H20)=0,"",IF(SUMPRODUCT(--ISNUMBER('Reported Financials'!E20:H20),--(E20:H20=""))=0,"OK","source missing")) -> OK
B21: Refunds | C21: 11 | F21: AR2024 p.206 | G21: AR2025 p.219 | H21: AR2025 p.219 | J21: Refunds | K21: found | M21: =IF(COUNT('Reported Financials'!E21:H21)=0,"",IF(SUMPRODUCT(--ISNUMBER('Reported Financials'!E21:H21),--(E21:H21=""))=0,"OK","source missing")) -> OK
B22: Government grants | C22: 11 | F22: AR2024 p.206 | G22: AR2025 p.219 | H22: AR2025 p.219 | J22: Government grants | K22: found | M22: =IF(COUNT('Reported Financials'!E22:H22)=0,"",IF(SUMPRODUCT(--ISNUMBER('Reported Financials'!E22:H22),--(E22:H22=""))=0,"OK","source missing")) -> OK
B23: Reversal of provisions | C23: 11 | F23: AR2024 p.206 | G23: AR2025 p.219 | H23: AR2025 p.219 | J23: Reversal of provisions | K23: found | M23: =IF(COUNT('Reported Financials'!E23:H23)=0,"",IF(SUMPRODUCT(--ISNUMBER('Reported Financials'!E23:H23),--(E23:H23=""))=0,"OK","source missing")) -> OK
B24: Residual/scrap disposal | C24: 11 | F24: AR2024 p.206 | G24: AR2025 p.219 | H24: AR2025 p.219 | J24: Residual/scrap disposal | K24: found | M24: =IF(COUNT('Reported Financials'!E24:H24)=0,"",IF(SUMPRODUCT(--ISNUMBER('Reported Financials'!E24:H24),--(E24:H24=""))=0,"OK","source missing")) -> OK
B25: Sundry rental agreements and leases | C25: 11 | F25: AR2024 p.206 | G25: AR2025 p.219 | H25: AR2025 p.219 | J25: Sundry rental agreements and leases | K25: found | M25: =IF(COUNT('Reported Financials'!E25:H25)=0,"",IF(SUMPRODUCT(--ISNUMBER('Reported Financials'!E25:H25),--(E25:H25=""))=0,"OK","source missing")) -> OK
B26: Disposal of fixed assets/divestments | C26: 11 | F26: AR2024 p.206 | G26: AR2025 p.219 | H26: AR2025 p.219 | J26: Disposal of fixed assets/divestments | K26: found | M26: =IF(COUNT('Reported Financials'!E26:H26)=0,"",IF(SUMPRODUCT(--ISNUMBER('Reported Financials'!E26:H26),--(E26:H26=""))=0,"OK","source missing")) -> OK
B27: Reversal of assets (excl. financial assets) | C27: 11 | F27: AR2024 p.206 | G27: AR2025 p.219 | H27: AR2025 p.219 | J27: Reversal of assets (excl. financial assets) | K27: found | M27: =IF(COUNT('Reported Financials'!E27:H27)=0,"",IF(SUMPRODUCT(--ISNUMBER('Reported Financials'!E27:H27),--(E27:H27=""))=0,"OK","source missing")) -> OK
B28: Miscellaneous operating income | C28: 11 | F28: AR2024 p.206 | G28: AR2025 p.219 | H28: AR2025 p.219 | J28: Miscellaneous operating income | K28: found | M28: =IF(COUNT('Reported Financials'!E28:H28)=0,"",IF(SUMPRODUCT(--ISNUMBER('Reported Financials'!E28:H28),--(E28:H28=""))=0,"OK","source missing")) -> OK
B29: Rounding / undisclosed difference | F29: formula | G29: formula | H29: formula | K29: derived (rounding / undisclosed difference)
B31: Cost of materials | C31: 12 | F31: sum of lines below | G31: sum of lines below | H31: sum of lines below | J31: Cost of materials | K31: derived (sum of note lines); printed figure in Checks | M31: =IF(COUNT('Reported Financials'!E31:H31)=0,"",IF(SUMPRODUCT(--ISNUMBER('Reported Financials'!E31:H31),--(E31:H31=""))=0,"OK","source missing")) -> OK
B32: Cost of raw materials, supplies and merchandise purchased | C32: 12 | F32: AR2024 p.207 | G32: AR2025 p.219 | H32: AR2025 p.219 | J32: Cost of raw materials, supplies and merchandise purchased | K32: found | M32: =IF(COUNT('Reported Financials'!E32:H32)=0,"",IF(SUMPRODUCT(--ISNUMBER('Reported Financials'!E32:H32),--(E32:H32=""))=0,"OK","source missing")) -> OK
B33: Cost of services purchased | C33: 12 | F33: AR2024 p.207 | G33: AR2025 p.219 | H33: AR2025 p.219 | J33: Cost of services purchased | K33: found | M33: =IF(COUNT('Reported Financials'!E33:H33)=0,"",IF(SUMPRODUCT(--ISNUMBER('Reported Financials'!E33:H33),--(E33:H33=""))=0,"OK","source missing")) -> OK
B34: Rounding / undisclosed difference | F34: formula | G34: formula | H34: formula | K34: derived (rounding / undisclosed difference)
B35: Personnel costs | C35: 13 | F35: sum of lines below | G35: sum of lines below | H35: sum of lines below | J35: Personnel costs | K35: derived (sum of note lines); printed figure in Checks | M35: =IF(COUNT('Reported Financials'!E35:H35)=0,"",IF(SUMPRODUCT(--ISNUMBER('Reported Financials'!E35:H35),--(E35:H35=""))=0,"OK","source missing")) -> OK
B36: Wages and salaries | C36: 13 | F36: AR2024 p.207 | G36: AR2025 p.219 | H36: AR2025 p.219 | J36: Wages and salaries | K36: found | M36: =IF(COUNT('Reported Financials'!E36:H36)=0,"",IF(SUMPRODUCT(--ISNUMBER('Reported Financials'!E36:H36),--(E36:H36=""))=0,"OK","source missing")) -> OK
B37: Social security and related employee benefits | C37: 13 | F37: AR2024 p.207 | G37: AR2025 p.219 | H37: AR2025 p.219 | J37: Social security and related employee benefits | K37: found | M37: =IF(COUNT('Reported Financials'!E37:H37)=0,"",IF(SUMPRODUCT(--ISNUMBER('Reported Financials'!E37:H37),--(E37:H37=""))=0,"OK","source missing")) -> OK
B38: Pension expenses | C38: 13 | F38: AR2024 p.207 | G38: AR2025 p.219 | H38: AR2025 p.219 | J38: Pension expenses | K38: found | M38: =IF(COUNT('Reported Financials'!E38:H38)=0,"",IF(SUMPRODUCT(--ISNUMBER('Reported Financials'!E38:H38),--(E38:H38=""))=0,"OK","source missing")) -> OK
B39: Expenses for redundancy plans, termination indemnities, partial retirement | C39: 13 | F39: AR2024 p.207 | G39: AR2025 p.219 | H39: AR2025 p.219 | J39: Expenses for redundancy plans, termination indemnities, partial retirement | K39: found | M39: =IF(COUNT('Reported Financials'!E39:H39)=0,"",IF(SUMPRODUCT(--ISNUMBER('Reported Financials'!E39:H39),--(E39:H39=""))=0,"OK","source missing")) -> OK
B40: Rounding / undisclosed difference | F40: formula | G40: formula | H40: formula | K40: derived (rounding / undisclosed difference)
B41: Amortization, depreciation and impairment | C41: 14 | F41: sum of lines below | G41: sum of lines below | H41: sum of lines below | J41: Amortization, depreciation and impairment | K41: derived (sum of note lines); printed figure in Checks | M41: =IF(COUNT('Reported Financials'!E41:H41)=0,"",IF(SUMPRODUCT(--ISNUMBER('Reported Financials'!E41:H41),--(E41:H41=""))=0,"OK","source missing")) -> OK
B42: Other intangible assets | C42: 14 | F42: AR2024 p.207 | G42: AR2025 p.220 | H42: AR2025 p.220 | J42: Other intangible assets | K42: found | M42: =IF(COUNT('Reported Financials'!E42:H42)=0,"",IF(SUMPRODUCT(--ISNUMBER('Reported Financials'!E42:H42),--(E42:H42=""))=0,"OK","source missing")) -> OK
B43: Right-of-use assets | C43: 14 | F43: AR2024 p.207 | G43: AR2025 p.220 | H43: AR2025 p.220 | J43: Right-of-use assets | K43: found | M43: =IF(COUNT('Reported Financials'!E43:H43)=0,"",IF(SUMPRODUCT(--ISNUMBER('Reported Financials'!E43:H43),--(E43:H43=""))=0,"OK","source missing")) -> OK
B44: Property, plant and equipment and investment property | C44: 14 | F44: AR2024 p.207 | G44: AR2025 p.220 | H44: AR2025 p.220 | J44: Property, plant and equipment and investment property | K44: found | M44: =IF(COUNT('Reported Financials'!E44:H44)=0,"",IF(SUMPRODUCT(--ISNUMBER('Reported Financials'!E44:H44),--(E44:H44=""))=0,"OK","source missing")) -> OK
B45: Rounding / undisclosed difference | F45: formula | G45: formula | H45: formula | K45: derived (rounding / undisclosed difference)
B46: % of sales | F46: formula | G46: formula | H46: formula | K46: derived (subtotal)
B47: Other operating expenses | C47: 15 | F47: sum of lines below | G47: sum of lines below | H47: sum of lines below | J47: Other operating expenses | K47: derived (sum of note lines); printed figure in Checks | M47: =IF(COUNT('Reported Financials'!E47:H47)=0,"",IF(SUMPRODUCT(--ISNUMBER('Reported Financials'!E47:H47),--(E47:H47=""))=0,"OK","source missing")) -> OK
B48: Operating costs and maintenance | C48: 15 | F48: AR2024 p.208 | G48: AR2025 p.220 | H48: AR2025 p.220 | J48: Operating costs and maintenance | K48: found | M48: =IF(COUNT('Reported Financials'!E48:H48)=0,"",IF(SUMPRODUCT(--ISNUMBER('Reported Financials'!E48:H48),--(E48:H48=""))=0,"OK","source missing")) -> OK
B49: IT costs | C49: 15 | F49: AR2024 p.208 | G49: AR2025 p.220 | H49: AR2025 p.220 | J49: IT costs | K49: found | M49: =IF(COUNT('Reported Financials'!E49:H49)=0,"",IF(SUMPRODUCT(--ISNUMBER('Reported Financials'!E49:H49),--(E49:H49=""))=0,"OK","source missing")) -> OK
B50: Distribution and advertising costs | C50: 15 | F50: AR2024 p.208 | G50: AR2025 p.220 | H50: AR2025 p.220 | J50: Distribution and advertising costs | K50: found | M50: =IF(COUNT('Reported Financials'!E50:H50)=0,"",IF(SUMPRODUCT(--ISNUMBER('Reported Financials'!E50:H50),--(E50:H50=""))=0,"OK","source missing")) -> OK
B51: Incidental personnel costs | C51: 15 | F51: AR2024 p.208 | G51: AR2025 p.220 | H51: AR2025 p.220 | J51: Incidental personnel costs | K51: found | M51: =IF(COUNT('Reported Financials'!E51:H51)=0,"",IF(SUMPRODUCT(--ISNUMBER('Reported Financials'!E51:H51),--(E51:H51=""))=0,"OK","source missing")) -> OK
B52: General administrative expenses | C52: 15 | F52: AR2024 p.208 | G52: AR2025 p.220 | H52: AR2025 p.220 | J52: General administrative expenses | K52: found | M52: =IF(COUNT('Reported Financials'!E52:H52)=0,"",IF(SUMPRODUCT(--ISNUMBER('Reported Financials'!E52:H52),--(E52:H52=""))=0,"OK","source missing")) -> OK
B53: Travel expenses | C53: 15 | F53: AR2024 p.208 | G53: AR2025 p.220 | H53: AR2025 p.220 | J53: Travel expenses | K53: found | M53: =IF(COUNT('Reported Financials'!E53:H53)=0,"",IF(SUMPRODUCT(--ISNUMBER('Reported Financials'!E53:H53),--(E53:H53=""))=0,"OK","source missing")) -> OK
B54: Insurances | C54: 15 | F54: AR2024 p.208 | G54: AR2025 p.220 | H54: AR2025 p.220 | J54: Insurances | K54: found | M54: =IF(COUNT('Reported Financials'!E54:H54)=0,"",IF(SUMPRODUCT(--ISNUMBER('Reported Financials'!E54:H54),--(E54:H54=""))=0,"OK","source missing")) -> OK
B55: Changes in / additions to other provisions | C55: 15 | F55: AR2024 p.208 | G55: AR2025 p.220 | H55: AR2025 p.220 | J55: Changes in / additions to other provisions | K55: found | M55: =IF(COUNT('Reported Financials'!E55:H55)=0,"",IF(SUMPRODUCT(--ISNUMBER('Reported Financials'!E55:H55),--(E55:H55=""))=0,"OK","source missing")) -> OK
B56: Audit, legal and consultancy fees | C56: 15 | F56: AR2024 p.208 | G56: AR2025 p.220 | H56: AR2025 p.220 | J56: Audit, legal and consultancy fees | K56: found | M56: =IF(COUNT('Reported Financials'!E56:H56)=0,"",IF(SUMPRODUCT(--ISNUMBER('Reported Financials'!E56:H56),--(E56:H56=""))=0,"OK","source missing")) -> OK
B57: Write-downs of receivables | C57: 15 | F57: AR2024 p.208 | G57: AR2025 p.220 | H57: AR2025 p.220 | J57: Write-downs of receivables | K57: found | M57: =IF(COUNT('Reported Financials'!E57:H57)=0,"",IF(SUMPRODUCT(--ISNUMBER('Reported Financials'!E57:H57),--(E57:H57=""))=0,"OK","source missing")) -> OK
B58: Rents, leases and ancillary costs | C58: 15 | F58: AR2024 p.208 | G58: AR2025 p.220 | H58: AR2025 p.220 | J58: Rents, leases and ancillary costs | K58: found | M58: =IF(COUNT('Reported Financials'!E58:H58)=0,"",IF(SUMPRODUCT(--ISNUMBER('Reported Financials'!E58:H58),--(E58:H58=""))=0,"OK","source missing")) -> OK
... B63: Miscellaneous operating expenses | C63: 15 | F63: AR2024 p.208 | G63: AR2025 p.220 | H63: AR2025 p.220 | J63: Miscellaneous operating expenses | K63: found | M63: =IF(COUNT('Reported Financials'!E63:H63)=0,"",IF(SUMPRODUCT(--ISNUMBER('Reported Financials'!E63:H63),--(E63:H63=""))=0,"OK","source missing")) -> OK
B64: Rounding / undisclosed difference | F64: formula | G64: formula | H64: formula | K64: derived (rounding / undisclosed difference)
B66: Result from investments accounted for using the equity method | C66: 22 | F66: AR2024 p.188 | G66: AR2025 p.199 | H66: AR2025 p.199 | J66: Result from investments accounted for using the equity method | K66: found | M66: =IF(COUNT('Reported Financials'!E66:H66)=0,"",IF(SUMPRODUCT(--ISNUMBER('Reported Financials'!E66:H66),--(E66:H66=""))=0,"OK","source missing")) -> OK
B67: Other financial result | F67: AR2024 p.188 | G67: AR2025 p.199 | H67: AR2025 p.199 | J67: Other financial result | K67: found | M67: =IF(COUNT('Reported Financials'!E67:H67)=0,"",IF(SUMPRODUCT(--ISNUMBER('Reported Financials'!E67:H67),--(E67:H67=""))=0,"OK","source missing")) -> OK
B68: Rounding difference to the printed subtotal | F68: formula | G68: formula | H68: formula | K68: derived (rounding / undisclosed difference)
B69: Earnings before interest and taxes (EBIT) | F69: formula | G69: formula | H69: formula | K69: derived (subtotal)
B70: EBIT margin | F70: formula | G70: formula | H70: formula | K70: derived (subtotal)
B71: Interest income | F71: AR2024 p.188 | G71: AR2025 p.199 | H71: AR2025 p.199 | J71: Interest income | K71: found | M71: =IF(COUNT('Reported Financials'!E71:H71)=0,"",IF(SUMPRODUCT(--ISNUMBER('Reported Financials'!E71:H71),--(E71:H71=""))=0,"OK","source missing")) -> OK
B72: Interest expenses | F72: AR2024 p.188 | G72: AR2025 p.199 | H72: AR2025 p.199 | J72: Interest expenses | K72: found | M72: =IF(COUNT('Reported Financials'!E72:H72)=0,"",IF(SUMPRODUCT(--ISNUMBER('Reported Financials'!E72:H72),--(E72:H72=""))=0,"OK","source missing")) -> OK
B73: Earnings before taxes (EBT) | F73: formula | G73: formula | H73: formula | K73: derived (subtotal)
B74: Income taxes | C74: 16 | F74: AR2024 p.188 | G74: AR2025 p.199 | H74: AR2025 p.199 | J74: Income taxes | K74: found | M74: =IF(COUNT('Reported Financials'!E74:H74)=0,"",IF(SUMPRODUCT(--ISNUMBER('Reported Financials'!E74:H74),--(E74:H74=""))=0,"OK","source missing")) -> OK
B75: Effective tax rate | F75: formula | G75: formula | H75: formula | K75: derived (subtotal)
B76: Earnings from continuing operations | F76: formula | G76: formula | H76: formula | K76: derived (subtotal)
B77: Earnings from discontinued operations | C77: 8 | F77: AR2024 p.188 | G77: AR2025 p.199 | H77: AR2025 p.199 | J77: Earnings from discontinued operations | K77: found | M77: =IF(COUNT('Reported Financials'!E77:H77)=0,"",IF(SUMPRODUCT(--ISNUMBER('Reported Financials'!E77:H77),--(E77:H77=""))=0,"OK","source missing")) -> OK
B78: Earnings after taxes | F78: formula | G78: formula | H78: formula | K78: derived (subtotal)
B79: Non-controlling interests | F79: AR2024 p.188 | G79: AR2025 p.199 | H79: AR2025 p.199 | J79: Non-controlling interests | K79: found | M79: =IF(COUNT('Reported Financials'!E79:H79)=0,"",IF(SUMPRODUCT(--ISNUMBER('Reported Financials'!E79:H79),--(E79:H79=""))=0,"OK","source missing")) -> OK
B80: Rheinmetall AG shareholders | F80: formula | G80: formula | H80: formula | K80: derived (subtotal)
B81: Profit margin | F81: formula | G81: formula | H81: formula | K81: derived (subtotal)
A83: x | B83: Additional information from the notes (included in the lines above)
B85: Amortisation from purchase price allocations (PPA) | C85: 14 | F85: AR2024 p.207 | G85: AR2025 p.220 | H85: AR2025 p.220 | J85: Amortisation from purchase price allocations (PPA) | K85: found | M85: =IF(COUNT('Reported Financials'!E85:H85)=0,"",IF(SUMPRODUCT(--ISNUMBER('Reported Financials'!E85:H85),--(E85:H85=""))=0,"OK","source missing")) -> OK
B86: Impairment losses | C86: 14 | F86: AR2024 p.208 | G86: AR2025 p.220 | H86: AR2025 p.220 | J86: Impairment losses | K86: found | M86: =IF(COUNT('Reported Financials'!E86:H86)=0,"",IF(SUMPRODUCT(--ISNUMBER('Reported Financials'!E86:H86),--(E86:H86=""))=0,"OK","source missing")) -> OK
B87: Net interest on pensions (interest cost − interest income on plan assets) | C87: 27 | F87: AR2024 p.224 | G87: AR2025 p.237 | H87: AR2025 p.237 | J87: Net interest on pensions (interest cost − interest income on plan assets) | K87: found | M87: =IF(COUNT('Reported Financials'!E87:H87)=0,"",IF(SUMPRODUCT(--ISNUMBER('Reported Financials'!E87:H87),--(E87:H87=""))=0,"OK","source missing")) -> OK
B88: Interest expenses from lease liabilities | C88: 19 | F88: AR2024 p.213 | G88: AR2025 p.225 | H88: AR2025 p.225 | J88: Interest expenses from lease liabilities | K88: found | M88: =IF(COUNT('Reported Financials'!E88:H88)=0,"",IF(SUMPRODUCT(--ISNUMBER('Reported Financials'!E88:H88),--(E88:H88=""))=0,"OK","source missing")) -> OK
B89: Shriram Pistons & Rings: gain on sale of share packages (31) + initial fair-value measurement of the remaining shares (22) | F89: AR2024 p.216 | G89: AR2025 p.55 | H89: AR2025 p.55 | J89: The profit of €31 million resulting from the sale of the share packages ... The same applied to the initial assessment of securities at fair value (€22 million). | K89: found | M89: =IF(COUNT('Reported Financials'!E89:H89)=0,"",IF(SUMPRODUCT(--ISNUMBER('Reported Financials'!E89:H89),--(E89:H89=""))=0,"OK","source missing")) -> OK
B90: Gain on sale of AIM shares (not adjusted by the company) | F90: AR2024 p.52 | G90: AR2025 p.55 | H90: AR2025 p.55 | J90: Gain on sale of AIM shares (not adjusted by the company) | K90: found (management report) | M90: =IF(COUNT('Reported Financials'!E90:H90)=0,"",IF(SUMPRODUCT(--ISNUMBER('Reported Financials'!E90:H90),--(E90:H90=""))=0,"OK","source missing")) -> OK
B91: Fair-value remeasurement gains in other financial result (2023: Shriram shares; 2025: previously held 40% interest in blackned, IFRS 3) | F91: AR2023 p.226 | G91: AR2025 p.56 | H91: AR2025 p.214 | J91: This resulted in an earnings effect of €15 million, which is recognised in other financial result. | K91: found | M91: =IF(COUNT('Reported Financials'!E91:H91)=0,"",IF(SUMPRODUCT(--ISNUMBER('Reported Financials'!E91:H91),--(E91:H91=""))=0,"OK","source missing")) -> OK
B92: Transaction costs for the acquisition of Loc Performance (management special item) | F92: AR2024 p.52 | G92: AR2025 p.55 | H92: AR2025 p.55 | J92: Special items from corporate transactions essentially related to transaction costs for the acquisition of Loc Performance (€6 million) | K92: found (management report) | M92: =IF(COUNT('Reported Financials'!E92:H92)=0,"",IF(SUMPRODUCT(--ISNUMBER('Reported Financials'!E92:H92),--(E92:H92=""))=0,"OK","source missing")) -> OK
B93: Earlier-period income taxes (included in income taxes) | C93: 16 | F93: AR2024 p.208 | G93: AR2025 p.220 | H93: AR2025 p.220 | J93: Earlier-period income taxes | K93: found | M93: =IF(COUNT('Reported Financials'!E93:H93)=0,"",IF(SUMPRODUCT(--ISNUMBER('Reported Financials'!E93:H93),--(E93:H93=""))=0,"OK","source missing")) -> OK
B94: Civilian business (Power Systems segment): external sales, as originally reported | F94: AR2024 p.193 | G94: AR2024 p.192 | J94: Segment report 2023 / 2024: External sales, Power Systems | K94: found (segment report) | M94: =IF(COUNT('Reported Financials'!E94:H94)=0,"",IF(SUMPRODUCT(--ISNUMBER('Reported Financials'!E94:H94),--(E94:H94=""))=0,"OK","source missing")) -> OK
B95: Civilian business (Power Systems segment): EBIT, as originally reported | F95: AR2024 p.193 | G95: AR2024 p.192 | J95: Segment report 2023 / 2024: EBIT, Power Systems | K95: found (segment report) | M95: =IF(COUNT('Reported Financials'!E95:H95)=0,"",IF(SUMPRODUCT(--ISNUMBER('Reported Financials'!E95:H95),--(E95:H95=""))=0,"OK","source missing")) -> OK
B96: Management special items: restructuring | F96: AR2024 p.52 | G96: AR2025 p.55 | H96: AR2025 p.55 | J96: Special items: restructuring / there of restructuring | K96: found (management report) | M96: =IF(COUNT('Reported Financials'!E96:H96)=0,"",IF(SUMPRODUCT(--ISNUMBER('Reported Financials'!E96:H96),--(E96:H96=""))=0,"OK","source missing")) -> OK
B97: Management special items: others | F97: AR2024 p.52 | G97: AR2025 p.55 | H97: AR2025 p.55 | J97: Special items: others / there of others | K97: found (management report) | M97: =IF(COUNT('Reported Financials'!E97:H97)=0,"",IF(SUMPRODUCT(--ISNUMBER('Reported Financials'!E97:H97),--(E97:H97=""))=0,"OK","source missing")) -> OK
B98: Insurance refund for production losses (Murcia), estimated unusual portion of refunds | C98: 11 | F98: AR2024 | G98: AR2025 | H98: AR2025 p.219; p.64 | J98: Refunds; 'insurance payments ... higher double-digit million euro amount' | K98: estimate (disclosed qualitatively) | M98: =IF(COUNT('Reported Financials'!E98:H98)=0,"",IF(SUMPRODUCT(--ISNUMBER('Reported Financials'!E98:H98),--(E98:H98=""))=0,"OK","source missing")) -> OK
B99: Provisions for structural measures (restructuring), in other provisions | C99: 28 | E99: AR2023 AR2024 p.226 (1/1/2023) | F99: AR2024 p.226 | G99: AR2025 p.240 | H99: AR2025 p.240 | J99: Other provisions: Structural measures | K99: found | M99: =IF(COUNT('Reported Financials'!E99:H99)=0,"",IF(SUMPRODUCT(--ISNUMBER('Reported Financials'!E99:H99),--(E99:H99=""))=0,"OK","source missing")) -> OK
B100: Discontinued operations: earnings before taxes | C100: 8 | F100: AR2024 p.204 | G100: AR2025 p.215 | H100: AR2025 p.215 | J100: Discontinued operations: earnings before taxes | K100: found | M100: =IF(COUNT('Reported Financials'!E100:H100)=0,"",IF(SUMPRODUCT(--ISNUMBER('Reported Financials'!E100:H100),--(E100:H100=""))=0,"OK","source missing")) -> OK
B101: Discontinued operations: income taxes | C101: 8 | F101: AR2024 p.204 | G101: AR2025 p.215 | H101: AR2025 p.215 | J101: Discontinued operations: income taxes | K101: found | M101: =IF(COUNT('Reported Financials'!E101:H101)=0,"",IF(SUMPRODUCT(--ISNUMBER('Reported Financials'!E101:H101),--(E101:H101=""))=0,"OK","source missing")) -> OK
B102: OCI before tax: remeasurement of net defined benefit liability from pensions | C102: 26 | F102: AR2024 p.221 | G102: AR2025 p.234 | H102: AR2025 p.234 | J102: OCI before tax: remeasurement of net defined benefit liability from pensions | K102: found | M102: =IF(COUNT('Reported Financials'!E102:H102)=0,"",IF(SUMPRODUCT(--ISNUMBER('Reported Financials'!E102:H102),--(E102:H102=""))=0,"OK","source missing")) -> OK
B103: OCI before tax: equity-method investments (not reclassified) | C103: 26 | F103: AR2024 p.221 | G103: AR2025 p.234 | H103: AR2025 p.234 | J103: OCI before tax: equity-method investments (not reclassified) | K103: found | M103: =IF(COUNT('Reported Financials'!E103:H103)=0,"",IF(SUMPRODUCT(--ISNUMBER('Reported Financials'!E103:H103),--(E103:H103=""))=0,"OK","source missing")) -> OK
B104: OCI before tax: change in value of derivatives (cash flow hedges) | C104: 26 | F104: AR2024 p.221 | G104: AR2025 p.234 | H104: AR2025 p.234 | J104: OCI before tax: change in value of derivatives (cash flow hedges) | K104: found | M104: =IF(COUNT('Reported Financials'!E104:H104)=0,"",IF(SUMPRODUCT(--ISNUMBER('Reported Financials'!E104:H104),--(E104:H104=""))=0,"OK","source missing")) -> OK
B105: OCI before tax: currency translation difference | C105: 26 | F105: AR2024 p.221 | G105: AR2025 p.234 | H105: AR2025 p.234 | J105: OCI before tax: currency translation difference | K105: found | M105: =IF(COUNT('Reported Financials'!E105:H105)=0,"",IF(SUMPRODUCT(--ISNUMBER('Reported Financials'!E105:H105),--(E105:H105=""))=0,"OK","source missing")) -> OK
B106: OCI before tax: equity-method investments (reclassified) | C106: 26 | F106: AR2024 p.221 | G106: AR2025 p.234 | H106: AR2025 p.234 | J106: OCI before tax: equity-method investments (reclassified) | K106: found | M106: =IF(COUNT('Reported Financials'!E106:H106)=0,"",IF(SUMPRODUCT(--ISNUMBER('Reported Financials'!E106:H106),--(E106:H106=""))=0,"OK","source missing")) -> OK
B107: Tax effect on other comprehensive income | C107: 26 | F107: AR2024 p.221 | G107: AR2025 p.234 | H107: AR2025 p.234 | J107: Tax effect on other comprehensive income | K107: found | M107: =IF(COUNT('Reported Financials'!E107:H107)=0,"",IF(SUMPRODUCT(--ISNUMBER('Reported Financials'!E107:H107),--(E107:H107=""))=0,"OK","source missing")) -> OK
B108: Research and development costs recognised as expenses | C108: 18 | F108: AR2024 p.212 | G108: AR2025 p.31 | H108: AR2025 p.31 | J108: Research and development costs recognised as expenses | K108: found | M108: =IF(COUNT('Reported Financials'!E108:H108)=0,"",IF(SUMPRODUCT(--ISNUMBER('Reported Financials'!E108:H108),--(E108:H108=""))=0,"OK","source missing")) -> OK
B109: Statutory tax rate | C109: 16 | F109: AR2024 p.208 | G109: AR2025 p.220 | H109: AR2025 p.220 | J109: Statutory tax rate | K109: found | M109: =IF(COUNT('Reported Financials'!E109:H109)=0,"",IF(SUMPRODUCT(--ISNUMBER('Reported Financials'!E109:H109),--(E109:H109=""))=0,"OK","source missing")) -> OK
A111: x | B111: Statement of Comprehensive Income
B113: Remeasurement of net defined benefit liability from pensions | F113: AR2024 p.188 | G113: AR2025 p.199 | H113: AR2025 p.199 | J113: Remeasurement of net defined benefit liability from pensions | K113: found | M113: =IF(COUNT('Reported Financials'!E113:H113)=0,"",IF(SUMPRODUCT(--ISNUMBER('Reported Financials'!E113:H113),--(E113:H113=""))=0,"OK","source missing")) -> OK
B114: Other comprehensive income from investments accounted for using the equity method (not reclassified) | F114: AR2024 p.188 | G114: AR2025 p.199 | H114: AR2025 p.199 | J114: Other comprehensive income from investments accounted for using the equity method (not reclassified) | K114: found | M114: =IF(COUNT('Reported Financials'!E114:H114)=0,"",IF(SUMPRODUCT(--ISNUMBER('Reported Financials'!E114:H114),--(E114:H114=""))=0,"OK","source missing")) -> OK
B115: Change in value of derivative financial instruments (cash flow hedge) | F115: AR2024 p.188 | G115: AR2025 p.199 | H115: AR2025 p.199 | J115: Change in value of derivative financial instruments (cash flow hedge) | K115: found | M115: =IF(COUNT('Reported Financials'!E115:H115)=0,"",IF(SUMPRODUCT(--ISNUMBER('Reported Financials'!E115:H115),--(E115:H115=""))=0,"OK","source missing")) -> OK
B116: Currency translation difference | F116: AR2024 p.188 | G116: AR2025 p.199 | H116: AR2025 p.199 | J116: Currency translation difference | K116: found | M116: =IF(COUNT('Reported Financials'!E116:H116)=0,"",IF(SUMPRODUCT(--ISNUMBER('Reported Financials'!E116:H116),--(E116:H116=""))=0,"OK","source missing")) -> OK
B117: Other comprehensive income from investments accounted for using the equity method (reclassified) | F117: AR2024 p.188 | G117: AR2025 p.199 | H117: AR2025 p.199 | J117: Other comprehensive income from investments accounted for using the equity method (reclassified) | K117: found | M117: =IF(COUNT('Reported Financials'!E117:H117)=0,"",IF(SUMPRODUCT(--ISNUMBER('Reported Financials'!E117:H117),--(E117:H117=""))=0,"OK","source missing")) -> OK
...

Sheet Log
B3: =MID(CELL("filename",B3),FIND("]",CELL("filename",B3))+1,256) -> Log
A7: x | B7: Issue log — one record per distinct conflict or analytical issue (kept when resolved)
B9: Issue ID | C9: Date | D9: Agent / module version | E9: Iteration(s) | F9: Task / request | G9: Conflict or analytical issue | H9: Evidence (document, page/note or tab/cells) | I9: Question we asked | J9: Rule we applied (course slide / prompt rule) | K9: Change made / reason unchanged | L9: Affected outputs | M9: Status and how we resolved it
B10: I-01 | C10: 46292 | D10: Agent v1.0 | E10: 1 | F10: Part 1 extraction | G10: Prior year restated in report T, T−2 not restated: 2024 is shown on the new perimeter (civilian business discontinued), 2023 on the old one. | H10: AR2025 p.199 (2024 restated) vs AR2024 p.188 (2023) | I10: Use the restated 2024 and the unrestated 2023? | J10: Latest published version of each year (Part 1 rule A1.2). | K10: 2024 taken from AR2025, 2023 from AR2024; comparability flagged in every T−1 vs T−2 change. | L10: All 2023→2024 changes; Ratio Summary screen | M10: Resolved — limitation disclosed
B11: I-02 | C11: 46292 | D11: Agent v1.0 | E11: 1 | F11: Part 1 extraction | G11: Footnote markers fused into numbers by text extraction: 'EBIT¹ 897' read as 1897; CFO 2024 read as '11,720' in AR2024; equity-method result 2023 read as '157'. | H11: AR2024 and AR2023 statements as text; see the comment column of Reported Financials (EBIT, equity-method result, cash flow from operating activities) | I11: — | J11: Rule A1.5 (5): every figure must pass a subtotal check or be confirmed twice. | K11: Corrected to 897 / 1,720 / 57; confirmed by the printed-subtotal checks. | L11: Reported Financials IS and CF | M11: Resolved
B12: I-03 | C12: 46292 | D12: Agent v1.0 | E12: 1 | F12: Part 1 extraction | G12: Capex 2024 differs between documents: 732 in the cash flow statement vs 697 in the key-figures table. | H12: AR2025 p.201 (cash flow) vs AR2025 p.3 (key figures) | I12: Which figure prevails? | J12: Awaiting: the cash flow statement is used as the primary statement. | K12: 732 used; difference shown in the comment column. | L12: Net capex, capex-to-sales, capex / D&A (P5) | M12: Resolved: we use the cash flow statement (732), because the statement prevails over the key-figures table. The 35 gap is explained in the comment column.
B13: I-04 | C13: 46292 | D13: Agent v1.0 | E13: 1 | F13: Part 2 R7 | G13: Interest expenses include the IFRS 15 financing component on customer advances; the amount is not disclosed. | H13: AR2025 p.56 | I13: Reclassify to operating without an amount? | J13: R7: leave in [C] and state it. | K13: Left in net financial expenses [C]; comment added. | L13: [C], IBUIT, Kd, NFE, ROE spreads | M13: Resolved: the financing interest on customer advances is not disclosed, so it stays in [C]. It slightly overstates our cost of debt, and we say so where Kd is shown.
B14: I-05 | C14: 46292 | D14: Agent v1.0 | E14: 1 | F14: Part 2 R4 | G14: Net interest on pensions sits inside interest expenses, while pensions are operating liabilities. | H14: Note 27, AR2025 p.237; AR2024 p.224 | I14: — | J14: R4 / B3: reclassify to personnel (coherence with the balance sheet). | K14: Pension interest moved to EBITDA; [C] excludes it. | L14: EBITDA, [A], [C] | M14: Resolved
B15: I-06 | C15: 46292 | D15: Agent v1.0 | E15: 1 | F15: Part 3 C1; Part 5 P5 | G15: Income statement presented by nature: no cost of sales, no gross profit; COGS and purchases not disclosed. | H15: AR2025 p.199 (IS by nature); note 12 | I15: Use proxies? | J15: C1: lens 1 'n.d.'. P5: COGS proxy = materials + services − inventory change; purchases = cost of materials and services. | K15: Lens 1 n.d.; DIO and DPO labelled as proxies. | L15: Lens 1, DIO, DPO, CCC | M15: Resolved: Rheinmetall reports costs by nature, so cost of sales cannot be rebuilt. Lens 1 is shown as not derivable, and DIO and DPO are labelled as proxies.
B16: I-07 | C16: 46292 | D16: Agent v1.0 | E16: 1 | F16: Part 4 B5 | G16: Current 'bonds' in the other-assets note are in fact shares in Shriram Pistons & Rings (strategic stake). | H16: Note 24, AR2023 p.227 | I16: — | J16: B5: strategic securities are non-operating, not liquidity. | K16: Classified as non-operating assets, not as short-term financial assets. | L16: NFP, non-operating assets, [B]/non-operating assets | M16: Resolved
B17: I-08 | C17: 46292 | D17: Agent v1.0 | E17: 1 | F17: Part 4 B5; Part 2 R9 | G17: Civilian business classified as held for sale at 31/12/2025 (IFRS 5). | H17: Note 8, AR2025 p.215–216 | I17: — | J17: B5 slide 19 option 1; R9 criterion 1. | K17: Net assets held for sale in non-operating assets; discontinued result before tax in unusual items; 2025 asset bases fall. | L17: Managerial BS 2025; P7 base; ROE 2025 | M17: Resolved
B18: I-09 | C18: 46292 | D18: Agent v1.0 | E18: 1 | F18: Part 5 P6 | G18: Trademarks are not disclosed separately from other intangible assets. | H18: Note 18, AR2025 p.223 | I18: — | J18: P6: remove goodwill only and state it. | K18: Adjusted ROI excludes goodwill only. | L18: Adjusted core ROI | M18: Resolved — limitation disclosed
B19: I-10 | C19: 46292 | D19: Agent v1.0 | E19: 1 | F19: Part 5 E7 | G19: Short-term interest and short-term financial debt are not disclosed separately, so the short-term borrowing rate cannot be computed. | H19: Note 29 (financial debts), IS interest line | I19: Use a market rate instead of the proxy? | J19: E7: proxy = financial expenses / financial liabilities × (1 − t); override cell available. | K19: Proxy used; override cell left blank. | L19: Implicit interest, ROOA | M19: Resolved: short-term interest is not disclosed, so we use the average cost of debt as our proxy and left an input cell for a market rate.
B20: I-11 | C20: 46292 | D20: Agent v1.0 | E20: 1 | F20: Part 5 checks | G20: Ratio identities (NOIC/NFO forms) differed by ~0.01 pp because the managerial BS did not tie exactly (NIC − (NFP + NE) = −1 to −2). | H20: Reformation & Profitability, check 'Managerial BS: net invested capital − (NFP + net equity)' (before I-13) | I20: — | J20: Solved at the source by I-13. | K20: After I-13 the managerial BS ties exactly; ratio tolerance reduced from 0.05 pp to 0.01 pp (floating-point only). All identities 0. | L20: ROI/ROE checks | M20: Resolved
B21: I-12 | C21: 46292 | D21: Agent v1.0 | E21: 1 | F21: Part 6 S0 | G21: Only three years: the material-change screen compares T with a single prior change, and that prior change is not like-for-like (I-01). | H21: Ratio Summary | I21: Is one prior change enough history? | J21: S0: flag, show both changes, no causes. | K21: Screen applied to T only; limitation stated under the Ratio Summary. | L21: Ratio Summary flags | M21: Resolved: with three years we can only compare 2025 with one earlier change. We state this limitation under the Ratio Summary.
... B71: I-62 | C71: 46296 | D71: Agent v2.0 draft (Module B) | E71: 1 | F71: Workbook layout | G71: Block 2 placed at the bottom of the existing tabs (your instruction). 'Reformation & Profitability' is now about 770 rows and does not fit one A3 page at Excel's 10% minimum scale. | H71: Page setup | I71: Separate tab or larger paper? | J71: House style: one page per tab | K71: Paper size A2 for that tab, fitted to one page. | L71: Printing only | M71: Resolved for now: printed on one A2 page; to revisit (D-06).
A74: x | B74: Closing disclosure — what a reader should know before relying on the workbook
B76: Figures not found | E76: IFRS 15 financing interest (I-04); short-term interest and short-term debt (I-10); trademarks (I-09); composition of the other financial result.; Block 2: restricted cash (not disclosed, note 25); asset breakdown of the 2025 acquisitions (I-60)
B77: Classifications awaiting a decision | E77: None. Every judgement call is resolved in the Log, with the reason for our choice.
B78: Inconsistencies between documents | E78: Capex 2024: 732 in the cash flow statement vs 697 in the key figures; we use 732 (I-03).; Block 2: §44A lease non-cash subtotal 2025 (89 printed vs 43 from components, I-55); §44A cash changes vs statement (I-56)
B79: Analyses that could not be completed | E79: Lens 1 (costs by function) and GMROI: not derivable, because the income statement is by nature (I-06).
B80: Group decisions taken during the work | E80: Year-end balance sheet basis; pension interest in operating costs (I-05); Shriram stake non-operating (I-07); statement prevails over notes, with rounding lines and a tolerance of 2 (I-13); restructuring and the Murcia insurance refund as unusual items (I-46, I-18); 100% fixed/variable per cost category (I-34); material-change factor k = 2.0.
B81: Assumptions and proxies we rely on | E81: COGS and purchases proxies for DIO and DPO (I-06, I-49); short-term borrowing rate proxy (I-10, I-52); estimated insurance refund of 97 (I-18); capex on a group perimeter (I-50).; Block 2: group perimeter for the cash flow (I-53); OCF undisclosed difference shown (I-54); Murcia refund assumed in cash (I-59); discontinued OCF as indicative proxy
B82: Open issues (count) | E82: =COUNTIF(M10:M71,"*review*")+COUNTIF(M10:M71,"Awaiting*")+COUNTIF(M10:M71,"Blocked*") -> 0
B83: Declared inputs not opened | E83: None. Every declared input of Modules A and B was opened (no time limit).
A85: x | B85: END

Sheet Decisions to revisit
B3: =MID(CELL("filename",B3),FIND("]",CELL("filename",B3))+1,256) -> Decisions to revisit
G6: Historicals
B7: (€ million) | C7: ID | E7: 2022A | F7: =TEXT(VALUE(LEFT(E7, 4)) + 1, "####")&IF(VALUE(LEFT(E7, 4)) + 1 <= 2025, "A", "P") -> 2023A | G7: =TEXT(VALUE(LEFT(F7, 4)) + 1, "####")&IF(VALUE(LEFT(F7, 4)) + 1 <= 2025, "A", "P") -> 2024A | H7: =TEXT(VALUE(LEFT(G7, 4)) + 1, "####")&IF(VALUE(LEFT(G7, 4)) + 1 <= 2025, "A", "P") -> 2025A | J7: What we did, why, and what to reconsider | K7: Go to
B8: Fiscal year end date | E8: 44926 | F8: 45291 | G8: 45657 | H8: 46022
A10: x | B10: Block 2 decisions to revisit (temporary tab — delete before the hand-in)
B12: Perimeter of the reformulated cash flow statement: the whole group, including discontinued operations | C12: D-01 | F12: ='Reformation & Profitability'!F569 -> -9 | G12: ='Reformation & Profitability'!G569 -> 191 | H12: ='Reformation & Profitability'!H569 -> 167 | J12: We reformulate the group statement because IAS 7 is printed line by line only for the group; continuing operations appear only as section totals. Block 1 EBITDA is for continuing operations, so we add a sourced line 'EBITDA of discontinued operations' (note 8) and show the continuing view only in the sustainable OCF (indicative). To reconsider: a continuing-only statement would need estimated working-capital and tax lines. | K12: Go to
B13: OCF is taken from the reported CFOA; the gap to EBITDA + ΔNOWC is shown as an 'undisclosed difference' | C13: D-02 | F13: ='Reformation & Profitability'!F576 -> 4 | G13: ='Reformation & Profitability'!G576 -> -65 | H13: ='Reformation & Profitability'!H576 -> -189 | J13: In plain words: we trust the printed cash flow from operating activities (the face of the statement prevails, as in Block 1). We get OCF by taking CFOA and moving out interest, taxes, dividends received and unusual items. When we rebuild OCF bottom-up from Block 1 EBITDA plus the reported working-capital lines, it does not add up exactly, because the statement does not separate tax accruals and some non-cash items. We show that gap on its own line instead of hiding it. Amounts per year are on the right. To reconsider: whether to split the gap further (e.g. using balance-sheet tax balances). | K13: Go to
B14: OCF before taxes as the headline; taxes paid among the other cash flows | C14: D-03 | F14: ='Reformation & Profitability'!F632 -> 782 | G14: ='Reformation & Profitability'!G632 -> 1793 | H14: ='Reformation & Profitability'!H632 -> 2268 | J14: Session 9 slides 5, 11 and 15 put taxes paid in the other cash flows (OFCF before taxes). OCF after taxes paid is shown as a memo (Session 8 slide 30). Unlevered FCF uses notional taxes on operating income (slide 14). | K14: Go to
B15: CAPEX = purchases − disposals of PP&E, intangibles and investment property, net of investment grants; new leases not in CAPEX | C15: D-04 | F15: ='Reformation & Profitability'!F736 -> -107 | G15: ='Reformation & Profitability'!G736 -> -44 | H15: ='Reformation & Profitability'!H736 -> -89 | J15: New leases are non-cash, so they enter the NFP bridge (case 3) and a memo 'CAPEX incl. new leases', not the cash statement. The 2024 government grant (35) reduces CAPEX because it finances the asset. | K15: Go to
B16: Hidden CAPEX: identifiable intangibles, PP&E and right-of-use assets at fair value; goodwill excluded; 2025 n.d. | C16: D-05 | F16: ='Reformation & Profitability'!F735 -> -644 | G16: ='Reformation & Profitability'!G735 -> -290 | H16: ='Reformation & Profitability'!H735 -> -51 | J16: We add the capital assets bought through acquisitions (Ketz, Session 8 slide 15) at their fair value in the purchase-price allocation, whatever the payment form. Goodwill is shown as a memo but not added. 2025: four immaterial acquisitions with no asset breakdown, so n.d. (not zero). Other small 2023–2024 acquisitions are not in the note tables. To reconsider: include goodwill as a sensitivity. | K16: Go to
B17: Block 2 placed at the bottom of the existing tabs; printing on one page | C17: D-06 | J17: As you asked, the cash flow statement sits at the bottom of 'Reported Financials' / 'Input financials' and the analysis at the bottom of 'Reformation & Profitability'. That tab is now about 770 rows: one A3 page would need a print scale below Excel's 10% minimum, so it is set to A2 paper, fitted to one page. To reconsider: a separate tab, or accept two pages. | K17: Go to
B18: Provisions for structural measures: whole class in class (b); its utilisation is an unusual cash flow | C18: D-07 | F18: ='Reformation & Profitability'!F644 -> -25 | G18: ='Reformation & Profitability'!G644 -> -18 | H18: ='Reformation & Profitability'!H644 -> -33 | J18: Block 1 moved the whole class out of NOWC (B3), although it mixes termination indemnities with partial retirement (the Module A fix #2 we promised). Its cash use (25 / 18 / 33) is therefore an unusual cash flow, while Block 1 treats only management's restructuring (1 / 2 / 7) as unusual, and the additions (21 / 30 / 40) sit inside EBITDA as personnel costs. To reconsider: keep partial retirement in NOWC and move only the redundancy part. | K18: Go to
B19: Murcia insurance refund (97) assumed received in cash in 2025 | C19: D-08 | F19: ='Reformation & Profitability'!F646 -> 0 | G19: ='Reformation & Profitability'!G646 -> 0 | H19: ='Reformation & Profitability'!H646 -> 97 | J19: Note 11 calls the refunds 'insurance payments for production losses' (AR2025 p.219), but the cash flow statement does not show whether all of it was received by 31 December. If part is still a receivable, OCF before unusual items is understated by the same amount. | K19: Go to
B20: Loc Performance transaction costs (6) assumed paid in 2024 | C20: D-09 | F20: ='Reformation & Profitability'!F645 -> 0 | G20: ='Reformation & Profitability'!G645 -> -6 | H20: ='Reformation & Profitability'!H645 -> 0 | J20: Expensed in 2024 (Block 1 unusual item); no payable disclosed. | K20: Go to
B21: Cash bottom line = IAS 7 cash, which includes cash of disposal groups | C21: D-10 | F21: ='Reformation & Profitability'!F620 -> -23 | G21: ='Reformation & Profitability'!G620 -> 0 | H21: ='Reformation & Profitability'!H620 -> -108 | J21: The statement's cash includes cash held for sale (23 at end-2022 and 2023, pistons; 108 at end-2025, civilian business). Block 1 NFP uses balance-sheet cash, so the reformulated statement deducts it and the NFP bridge shows its change. | K21: Go to
B22: §44A reconciliation 2025: printed lease non-cash subtotal (89) ≠ its components (43) | C22: D-11 | J22: We use the components, because they agree with the closing balance (difference 1). The report's subtotal error is shown in the checks of 'Reported Financials' and logged (I-55), not counted as a failed check. | K22: Go to
B23: §44A cash changes differ from the financing lines of the statement (2023: 6; 2024: 14) | C23: D-12 | F23: ='Reformation & Profitability'!F682 -> 6 | G23: ='Reformation & Profitability'!G682 -> 14 | H23: ='Reformation & Profitability'!H682 -> 0 | J23: The NFP bridge uses the statement for the cash flows and §44A for the non-cash changes; the difference is a separate, labelled line. | K23: Go to
B24: Unlevered FCF: notional taxes = t × ([A] + equity-method result), same base and t as NOPAT | C24: D-13 | F24: ='Reformation & Profitability'!F696 -> -194.92025 | G24: ='Reformation & Profitability'!G696 -> -356.3964 | H24: ='Reformation & Profitability'!H696 -> -383.77545 | J24: t is the tax rate of continuing operations (M11, row 463). The difference to taxes paid is a derived line in the FCFE bridge. | K24: Go to
B25: Dividends from equity-accounted investments are other cash flows, not OCF | C25: D-14 | F25: ='Reformation & Profitability'!F591 -> 29 | G25: ='Reformation & Profitability'!G591 -> 16 | H25: ='Reformation & Profitability'!H591 -> 21 | J25: The equity-method result is non-core [B] in Block 1, so its cash follows (Session 9 slide 6 coherence). | K25: Go to
B26: EBITDA of the discontinued pistons business derived from EBT, the write-down and the deconsolidation result | C26: D-15 | F26: ='Reformation & Profitability'!F569 -> -9 | G26: ='Reformation & Profitability'!G569 -> 191 | H26: ='Reformation & Profitability'!H569 -> 167 | J26: The note gives no D&A (no depreciation after the IFRS 5 classification in 2021) and no interest split, so EBITDA = EBT − write-down − deconsolidation result. | K26: Go to
A28: x | B28: Checks
B30: No numerical checks: this tab only lists decisions. Amounts are links to 'Reformation & Profitability'.
B31: Overall status | J31: ALL OK
A33: x | B33: END

Sheet _CIQHiddenCacheSheet
A1: 6 | B1: BAABTAVMT0NBTAFI/////wFQGAAAABtDSVEuVFNYOkFUWi5JUV9DT01QQU5ZX05BTUUBAAAAEq8vCAMAAAAMQXJpdHppYSBJbmMuAF6Tvf5OGt8Ib4TZ/k4a3wgfQ0lRLkVOWFRQQTpTTUNQLklRX0NPTVBBTllfTkFNRQEAAAAzecQGAwAAAAlTTUNQIFMuQS4AXpO9/k4a3whvhNn+ThrfCB5DSVEuSExTRTpNRUtLTy5JUV9DT01QQU5ZX05BTUUBAAAA9px7AAMAAAANTWFyaW1la2tvIE95agBek73+ThrfCG+E2f5OGt8IHENJUS5OWVNFOlRQUi5JUV9DT01QQU5ZX05BTUUBAAAA7QgIAAMAAAAOVGFwZXN0cnksIEluYy4AXpO9/k4a3whvhNn+ThrfCCdDSVEuVFNYOkFUWi5JUV9NQVJLRVRDQVAuMzEvMTIvMjAyNC5ES0sBAAAAEq8vCAIAAAAQMzAyMDEsNjgzMjM4ODYxNAEGAAAABQAAAAExAQAAAAstMTk3Mzg2NTE2MQMAAAACNDICAAAABjEwMDA1NAQAAAABMAcAAAAKMTIvMzEvMjAyNF6Tvf5OGt8I6FzZ/k4a3wgrQ0lRLkVOWFRQQTpTTUNQLklRX01BUktFVENBUC4zMS8xMi8yMDI0LkRLSwEAAAAzecQGAgAAABAyMDY0LDcyNjY1ODI4OTkzAQYAAAAFAAAAATEBAAAACy0xOTgzNzc2ODQzAwAAAAI0MgIAAAAGMTAwMDU0BAAAAAEwBwAAAAoxMi8zMS8yMDI0XpO9/k4a3whvhNn+ThrfCCpDSVEuSExTRTpNRUtLTy5JUV9NQVJLRVRDQVAuMzEvMTIvMjAyNC5ES0sBAAAA9px7AAIAAAAQMzY2NywxNzI4 | C1: NzA4MDEzOQEGAAAABQAAAAExAQAAAAstMTk3MDQ5Mjg0MgMAAAACNDICAAAABjEwMDA1NAQAAAABMAcAAAAKMTIvMzEvMjAyNF6Tvf5OGt8Ib4TZ/k4a3wgoQ0lRLk5ZU0U6VFBSLklRX01BUktFVENBUC4zMS8xMi8yMDI0LkRLSwEAAADtCAgAAgAAABAxMDc4NTUsNTk4NjE5NTkyAQYAAAAFAAAAATEBAAAACy0xOTcwMzQ4NDk1AwAAAAI0MgIAAAAGMTAwMDU0BAAAAAEwBwAAAAoxMi8zMS8yMDI0XpO9/k4a3whvhNn+ThrfCCJDSVEuVFNYOkFUWi5JUV9CRVRBXzVZUi4zMS8xMi8yMDI0AQAAABKvLwgCAAAAEDEsNzUzMzU4MTgyOTAxMDcAXpO9/k4a3whvhNn+ThrfCCZDSVEuRU5YVFBBOlNNQ1AuSVFfQkVUQV81WVIuMzEvMTIvMjAyNAEAAAAzecQGAgAAABAxLDcxMzQxMzIzMzA5MDU2AF6Tvf5OGt8Ib4TZ/k4a3wglQ0lRLkhMU0U6TUVLS08uSVFfQkVUQV81WVIuMzEvMTIvMjAyNAEAAAD2nHsAAgAAABAxLDI1NTQ2OTM4NDczMzkzAF6Tvf5OGt8Ib4TZ/k4a3wgjQ0lRLk5ZU0U6VFBSLklRX0JFVEFfNVlSLjMxLzEyLzIwMjQBAAAA7QgIAAIAAAAQMSw2MDU2NjUwMjE4NTkwNgBek73+ThrfCG+E2f5OGt8IMENJUS5UU1g6QVRaLklRX1RPVEFMX0RFQlQuSVFfRlEuMzEvMTIvMjAyNC4uLkRLSwEAAAASry8IAgAAAAs0NTEyLDc5ODk5OQEIAAAABQAAAAExAQAAAAstMTkxMDUwODcwMAMAAAACNDIC | D1: AAAABDQxNzMEAAAAATAHAAAACjEyLzMxLzIwMjQIAAAACTEyLzEvMjAyNAkAAAABMF6Tvf5OGt8Ib4TZ/k4a3wgeQ0lRLlRTWDpBVFouSVFfRklMSU5HX0NVUlJFTkNZAQAAABKvLwgDAAAAA0NBRABek73+ThrfCG+E2f5OGt8IIkNJUS5FTlhUUEE6U01DUC5JUV9GSUxJTkdfQ1VSUkVOQ1kBAAAAM3nEBgMAAAADRVVSAF6Tvf5OGt8Ib4TZ/k4a3wghQ0lRLkhMU0U6TUVLS08uSVFfRklMSU5HX0NVUlJFTkNZAQAAAPacewADAAAAA0VVUgBek73+ThrfCG+E2f5OGt8IH0NJUS5OWVNFOlRQUi5JUV9GSUxJTkdfQ1VSUkVOQ1kBAAAA7QgIAAMAAAADVVNEAF6Tvf5OGt8I6FzZ/k4a3wg0Q0lRLkVOWFRQQTpTTUNQLklRX1RPVEFMX0RFQlQuSVFfRlEuMzEvMTIvMjAyNC4uLkRLSwEAAAAzecQGAgAAAAo1NDQzLDQyNjI5AQgAAAAFAAAAATEBAAAACy0xOTA0MDU3MDU1AwAAAAI0MgIAAAAENDE3MwQAAAABMAcAAAAKMTIvMzEvMjAyNAgAAAAKMTIvMzEvMjAyNAkAAAABMF6Tvf5OGt8Ib4TZ/k4a3wgzQ0lRLkhMU0U6TUVLS08uSVFfVE9UQUxfREVCVC5JUV9GUS4zMS8xMi8yMDI0Li4uREtLAQAAAPacewACAAAACjIyOCwyMDc3NjEBCAAAAAUAAAABMQEAAAALLTE5MDA2OTA4MTcDAAAAAjQyAgAAAAQ0MTczBAAAAAEwBwAAAAoxMi8zMS8yMDI0CAAAAAoxMi8zMS8yMDI0CQAAAAEwXpO9/k4a3whvhNn+Thrf | E1: CDFDSVEuTllTRTpUUFIuSVFfVE9UQUxfREVCVC5JUV9GUS4zMS8xMi8yMDI0Li4uREtLAQAAAO0ICAACAAAADDI5MzY5LDA0ODAyMgEIAAAABQAAAAExAQAAAAstMTkwNzg3MTEzOAMAAAACNDICAAAABDQxNzMEAAAAATAHAAAACjEyLzMxLzIwMjQIAAAACjEyLzI4LzIwMjQJAAAAATBek73+ThrfCG+E2f5OGt8IMENJUS5UU1g6QVRaLklRX0NBU0hfRVFVSVYuSVFfRlEuMzEvMTIvMjAyNC4uLkRLSwEAAAASry8IAgAAAAsxMDQzLDk5OTI2NQEIAAAABQAAAAExAQAAAAstMTkxMDUwODcwMAMAAAACNDICAAAABDEwOTYEAAAAATAHAAAACjEyLzMxLzIwMjQIAAAACTEyLzEvMjAyNAkAAAABMF6Tvf5OGt8Ib4TZ/k4a3wg0Q0lRLkVOWFRQQTpTTUNQLklRX0NBU0hfRVFVSVYuSVFfRlEuMzEvMTIvMjAyNC4uLkRLSwEAAAAzecQGAgAAAAozNjEsNzAxODQzAQgAAAAFAAAAATEBAAAACy0xOTA0MDU3MDU1AwAAAAI0MgIAAAAEMTA5NgQAAAABMAcAAAAKMTIvMzEvMjAyNAgAAAAKMTIvMzEvMjAyNAkAAAABMF6Tvf5OGt8Ib4TZ/k4a3wgzQ0lRLkhMU0U6TUVLS08uSVFfQ0FTSF9FUVVJVi5JUV9GUS4zMS8xMi8yMDI0Li4uREtLAQAAAPacewACAAAACjMwMSwyOTM5MDYBCAAAAAUAAAABMQEAAAALLTE5MDA2OTA4MTcDAAAAAjQyAgAAAAQxMDk2BAAAAAEwBwAAAAoxMi8zMS8yMDI0CAAAAAoxMi8zMS8yMDI0 | F1: CQAAAAEwXpO9/k4a3wjoXNn+ThrfCDFDSVEuTllTRTpUUFIuSVFfQ0FTSF9FUVVJVi5JUV9GUS4zMS8xMi8yMDI0Li4uREtLAQAAAO0ICAACAAAACzcwMzIsOTUyMjc4AQgAAAAFAAAAATEBAAAACy0xOTA3ODcxMTM4AwAAAAI0MgIAAAAEMTA5NgQAAAABMAcAAAAKMTIvMzEvMjAyNAgAAAAKMTIvMjgvMjAyNAkAAAABMF6Tvf5OGt8I6FzZ/k4a3wg=
